{
  "name": "Eye agate",
  "type": "loot",
  "system": {
    "description": {
      "value": "<div class=\"ddb\">\n<p>A translucent gemstone with circles of gray, white, brown, blue, or green worth 10 gold pieces</p>\n</div>",
      "chat": ""
    },
    "source": {
      "book": "Player’s Handbook",
      "page": "",
      "license": "",
      "custom": ""
    },
    "identified": true,
    "unidentified": {
      "description": ""
    },
    "container": null,
    "quantity": 1,
    "weight": 0,
    "price": {
      "value": 10,
      "denomination": "gp"
    },
    "rarity": "",
    "properties": [],
    "type": {
      "value": "gem",
      "subtype": ""
    }
  },
  "flags": {
    "ddbimporter": {
      "dndbeyond": {
        "type": "Gemstone",
        "isConsumable": false,
        "isContainer": false,
        "isCustomItem": false,
        "isHomebrew": false,
        "isMonkWeapon": false,
        "isPack": false,
        "levelInfusionGranted": null,
        "tags": [],
        "sources": [
          {
            "sourceId": 1,
            "pageNumber": null,
            "sourceType": 2
          },
          {
            "sourceId": 2,
            "pageNumber": null,
            "sourceType": 1
          }
        ],
        "stackable": true
      },
      "id": 0,
      "entityTypeId": 0,
      "definitionEntityTypeId": 2103445194,
      "definitionId": 273,
      "originalName": "Eye agate",
      "version": "5.1.27"
    },
    "midi-qol": {
      "removeAttackDamageButtons": "default"
    },
    "midiProperties": {
      "confirmTargets": "default"
    }
  },
  "effects": [],
  "img": "icons/commodities/gems/gem-rough-oval-orange.webp",
  "folder": "mTEN1Y2VtFRaehzX",
  "ownership": {
    "default": 0,
    "6yhz13iFYYklKtgA": 3
  },
  "_stats": {
    "systemId": "dnd5e",
    "systemVersion": "3.3.1",
    "coreVersion": "12.331",
    "createdTime": 1721268424485,
    "modifiedTime": 1730038966903,
    "lastModifiedBy": "6yhz13iFYYklKtgA",
    "compendiumSource": null,
    "duplicateSource": null
  },
  "_id": "3rZlKQr3avpU4pMB",
  "sort": 0,
  "_key": "!items!3rZlKQr3avpU4pMB"
}
