{
  "name": "Abominable Yeti",
  "type": "npc",
  "_id": "K3sycUIZ1MXTp82C",
  "img": "https://www.dndbeyond.com/avatars/4675/676/636747837839875603.jpeg",
  "system": {
    "currency": {
      "pp": 0,
      "gp": 0,
      "ep": 0,
      "sp": 0,
      "cp": 0
    },
    "abilities": {
      "str": {
        "value": 24,
        "proficient": 0,
        "max": null,
        "bonuses": {
          "check": "",
          "save": ""
        }
      },
      "dex": {
        "value": 10,
        "proficient": 0,
        "max": null,
        "bonuses": {
          "check": "",
          "save": ""
        }
      },
      "con": {
        "value": 22,
        "proficient": 0,
        "max": null,
        "bonuses": {
          "check": "",
          "save": ""
        }
      },
      "int": {
        "value": 9,
        "proficient": 0,
        "max": null,
        "bonuses": {
          "check": "",
          "save": ""
        }
      },
      "wis": {
        "value": 13,
        "proficient": 0,
        "max": null,
        "bonuses": {
          "check": "",
          "save": ""
        }
      },
      "cha": {
        "value": 9,
        "proficient": 0,
        "max": null,
        "bonuses": {
          "check": "",
          "save": ""
        }
      }
    },
    "bonuses": {
      "mwak": {
        "attack": "",
        "damage": ""
      },
      "rwak": {
        "attack": "",
        "damage": ""
      },
      "msak": {
        "attack": "",
        "damage": ""
      },
      "rsak": {
        "attack": "",
        "damage": ""
      },
      "abilities": {
        "check": "",
        "save": "",
        "skill": ""
      },
      "spell": {
        "dc": ""
      }
    },
    "skills": {
      "acr": {
        "ability": "dex",
        "roll": {
          "min": null,
          "max": null,
          "mode": 0
        },
        "value": 0,
        "bonuses": {
          "check": "",
          "passive": ""
        }
      },
      "ani": {
        "ability": "wis",
        "roll": {
          "min": null,
          "max": null,
          "mode": 0
        },
        "value": 0,
        "bonuses": {
          "check": "",
          "passive": ""
        }
      },
      "arc": {
        "ability": "int",
        "roll": {
          "min": null,
          "max": null,
          "mode": 0
        },
        "value": 0,
        "bonuses": {
          "check": "",
          "passive": ""
        }
      },
      "ath": {
        "ability": "str",
        "roll": {
          "min": null,
          "max": null,
          "mode": 0
        },
        "value": 0,
        "bonuses": {
          "check": "",
          "passive": ""
        }
      },
      "dec": {
        "ability": "cha",
        "roll": {
          "min": null,
          "max": null,
          "mode": 0
        },
        "value": 0,
        "bonuses": {
          "check": "",
          "passive": ""
        }
      },
      "his": {
        "ability": "int",
        "roll": {
          "min": null,
          "max": null,
          "mode": 0
        },
        "value": 0,
        "bonuses": {
          "check": "",
          "passive": ""
        }
      },
      "ins": {
        "ability": "wis",
        "roll": {
          "min": null,
          "max": null,
          "mode": 0
        },
        "value": 0,
        "bonuses": {
          "check": "",
          "passive": ""
        }
      },
      "itm": {
        "ability": "cha",
        "roll": {
          "min": null,
          "max": null,
          "mode": 0
        },
        "value": 0,
        "bonuses": {
          "check": "",
          "passive": ""
        }
      },
      "inv": {
        "ability": "int",
        "roll": {
          "min": null,
          "max": null,
          "mode": 0
        },
        "value": 0,
        "bonuses": {
          "check": "",
          "passive": ""
        }
      },
      "med": {
        "ability": "wis",
        "roll": {
          "min": null,
          "max": null,
          "mode": 0
        },
        "value": 0,
        "bonuses": {
          "check": "",
          "passive": ""
        }
      },
      "nat": {
        "ability": "int",
        "roll": {
          "min": null,
          "max": null,
          "mode": 0
        },
        "value": 0,
        "bonuses": {
          "check": "",
          "passive": ""
        }
      },
      "prc": {
        "ability": "wis",
        "roll": {
          "min": null,
          "max": null,
          "mode": 0
        },
        "value": 1,
        "bonuses": {
          "check": "",
          "passive": ""
        }
      },
      "prf": {
        "ability": "cha",
        "roll": {
          "min": null,
          "max": null,
          "mode": 0
        },
        "value": 0,
        "bonuses": {
          "check": "",
          "passive": ""
        }
      },
      "per": {
        "ability": "cha",
        "roll": {
          "min": null,
          "max": null,
          "mode": 0
        },
        "value": 0,
        "bonuses": {
          "check": "",
          "passive": ""
        }
      },
      "rel": {
        "ability": "int",
        "roll": {
          "min": null,
          "max": null,
          "mode": 0
        },
        "value": 0,
        "bonuses": {
          "check": "",
          "passive": ""
        }
      },
      "slt": {
        "ability": "dex",
        "roll": {
          "min": null,
          "max": null,
          "mode": 0
        },
        "value": 0,
        "bonuses": {
          "check": "",
          "passive": ""
        }
      },
      "ste": {
        "ability": "dex",
        "roll": {
          "min": null,
          "max": null,
          "mode": 0
        },
        "value": 1,
        "bonuses": {
          "check": "",
          "passive": ""
        }
      },
      "sur": {
        "ability": "wis",
        "roll": {
          "min": null,
          "max": null,
          "mode": 0
        },
        "value": 0,
        "bonuses": {
          "check": "",
          "passive": ""
        }
      }
    },
    "tools": {},
    "spells": {
      "spell1": {
        "value": 0,
        "override": null
      },
      "spell2": {
        "value": 0,
        "override": null
      },
      "spell3": {
        "value": 0,
        "override": null
      },
      "spell4": {
        "value": 0,
        "override": null
      },
      "spell5": {
        "value": 0,
        "override": null
      },
      "spell6": {
        "value": 0,
        "override": null
      },
      "spell7": {
        "value": 0,
        "override": null
      },
      "spell8": {
        "value": 0,
        "override": null
      },
      "spell9": {
        "value": 0,
        "override": null
      },
      "pact": {
        "value": 0,
        "override": null
      }
    },
    "attributes": {
      "init": {
        "ability": "",
        "roll": {
          "min": null,
          "max": null,
          "mode": 0
        },
        "bonus": ""
      },
      "movement": {
        "burrow": null,
        "climb": 40,
        "fly": null,
        "swim": null,
        "walk": 40,
        "units": "ft",
        "hover": false
      },
      "attunement": {
        "max": 3
      },
      "senses": {
        "darkvision": 60,
        "blindsight": 0,
        "tremorsense": 0,
        "truesight": 0,
        "units": "ft",
        "special": ""
      },
      "spellcasting": "int",
      "exhaustion": 0,
      "concentration": {
        "ability": "",
        "roll": {
          "min": null,
          "max": null,
          "mode": 0
        },
        "bonuses": {
          "save": ""
        },
        "limit": 1
      },
      "ac": {
        "flat": 15,
        "calc": "natural",
        "formula": ""
      },
      "hp": {
        "value": 137,
        "max": 137,
        "temp": 0,
        "tempmax": 0,
        "formula": "11d12 + 66"
      },
      "death": {
        "ability": "",
        "roll": {
          "min": null,
          "max": null,
          "mode": 0
        },
        "success": 0,
        "failure": 0
      }
    },
    "details": {
      "biography": {
        "value": "",
        "public": ""
      },
      "alignment": "Chaotic Evil",
      "race": null,
      "type": {
        "value": "monstrosity",
        "subtype": ""
      },
      "environment": "Arctic",
      "cr": 9,
      "spellLevel": 0,
      "source": {
        "book": "Monster Manual",
        "page": "306",
        "custom": "",
        "license": ""
      }
    },
    "resources": {
      "legact": {
        "value": 0,
        "max": 0
      },
      "legres": {
        "value": 0,
        "max": 0
      },
      "lair": {
        "value": false,
        "initiative": null
      }
    },
    "traits": {
      "size": "huge",
      "di": {
        "value": [
          "cold"
        ],
        "bypasses": [],
        "custom": ""
      },
      "dr": {
        "value": [],
        "bypasses": [],
        "custom": ""
      },
      "dv": {
        "value": [],
        "bypasses": [],
        "custom": ""
      },
      "dm": {
        "amount": {},
        "bypasses": []
      },
      "ci": {
        "value": [],
        "custom": ""
      },
      "languages": {
        "value": [
          "yeti"
        ],
        "custom": ""
      }
    }
  },
  "prototypeToken": {
    "name": "Abominable Yeti",
    "displayName": 20,
    "actorLink": false,
    "appendNumber": false,
    "prependAdjective": false,
    "texture": {
      "src": "ddb-images/other/npc-generic-token-monstrosity.jpeg",
      "scaleX": 1,
      "scaleY": 1,
      "offsetX": 0,
      "offsetY": 0,
      "rotation": 0
    },
    "width": 3,
    "height": 3,
    "lockRotation": false,
    "rotation": 0,
    "alpha": 1,
    "disposition": -1,
    "displayBars": 20,
    "bar1": {
      "attribute": "attributes.hp"
    },
    "bar2": {
      "attribute": null
    },
    "light": {
      "alpha": 0.5,
      "angle": 360,
      "bright": 0,
      "coloration": 1,
      "dim": 0,
      "attenuation": 0.5,
      "luminosity": 0.5,
      "saturation": 0,
      "contrast": 0,
      "shadows": 0,
      "animation": {
        "type": null,
        "speed": 5,
        "intensity": 5,
        "reverse": false
      },
      "darkness": {
        "min": 0,
        "max": 1
      }
    },
    "sight": {
      "enabled": false,
      "range": 60,
      "angle": 360,
      "visionMode": "darkvision",
      "color": null,
      "attenuation": 0,
      "brightness": 0,
      "saturation": -1,
      "contrast": 0
    },
    "detectionModes": [],
    "flags": {
      "monks-tokenbar": {
        "include": "default"
      },
      "tagger": {
        "tags": [
          "dndbeyond",
          "ddb-importer",
          "monstrosity"
        ]
      }
    },
    "randomImg": false
  },
  "items": [
    {
      "_id": "ylPaU5BtrXaTPb3u",
      "name": "Multiattack",
      "type": "feat",
      "system": {
        "description": {
          "value": "<div class=\"ddb\">\n<section class=\"secret\">\n<p> The yeti can use its Chilling Gaze and makes two claw attacks.</p>\n</section>\nThe [[lookup @name]] uses [[lookup @item.name]].\n</div>",
          "chat": ""
        },
        "source": {
          "book": "Monster Manual",
          "page": "306",
          "custom": "",
          "license": ""
        },
        "activation": {
          "type": "action",
          "cost": 1,
          "condition": ""
        },
        "duration": {
          "value": "",
          "units": "inst"
        },
        "cover": null,
        "crewed": false,
        "target": {
          "value": null,
          "width": null,
          "units": "",
          "type": "",
          "prompt": true
        },
        "range": {
          "value": null,
          "long": null,
          "units": ""
        },
        "uses": {
          "value": null,
          "max": "",
          "per": null,
          "recovery": "",
          "prompt": true
        },
        "consume": {
          "type": "",
          "target": null,
          "amount": null,
          "scale": false
        },
        "ability": null,
        "actionType": null,
        "attack": {
          "bonus": "",
          "flat": false
        },
        "chatFlavor": "",
        "critical": {
          "threshold": null,
          "damage": ""
        },
        "damage": {
          "parts": [],
          "versatile": ""
        },
        "formula": "",
        "save": {
          "dc": null,
          "ability": "",
          "scaling": "flat"
        },
        "summons": null,
        "type": {
          "value": "monster",
          "subtype": ""
        },
        "properties": [],
        "requirements": "",
        "recharge": {
          "value": null,
          "charged": false
        }
      },
      "effects": [],
      "flags": {
        "ddbimporter": {
          "levelBonus": false,
          "dndbeyond": {}
        },
        "monsterMunch": {
          "titleHTML": "<strong>Multiattack.</strong>",
          "fullName": "Multiattack.",
          "actionCopy": false,
          "type": "action",
          "actionInfo": {
            "damage": {
              "parts": [],
              "versatile": ""
            },
            "baseAbility": null,
            "toHit": 0,
            "proficient": false,
            "extraAttackBonus": 0
          }
        },
        "midi-qol": {
          "removeAttackDamageButtons": "default"
        },
        "midiProperties": {
          "confirmTargets": "default"
        }
      },
      "img": "icons/skills/melee/strike-weapons-orange.webp",
      "folder": null,
      "sort": 0,
      "ownership": {
        "default": 0
      },
      "_stats": {
        "systemId": null,
        "systemVersion": null,
        "coreVersion": null,
        "createdTime": null,
        "modifiedTime": null,
        "lastModifiedBy": null
      },
      "_key": "!actors.items!K3sycUIZ1MXTp82C.ylPaU5BtrXaTPb3u"
    },
    {
      "_id": "3G0qoXERQeu7fsfd",
      "name": "Claw",
      "type": "weapon",
      "system": {
        "description": {
          "value": "<div class=\"ddb\">\n<section class=\"secret\">\n<p><em><strong></strong> Melee Weapon Attack:</em> +11 to hit, reach 5 ft., one target. <em>Hit:</em> [[/damage 2d6 + @mod type=slashing average=true]] damage plus [[/damage 2d6 type=cold average=true]] damage.</p>\n</section>\nThe [[lookup @name]] attacks with its [[lookup @item.name]].\n</div>",
          "chat": ""
        },
        "source": {
          "book": "Monster Manual",
          "page": "306",
          "custom": "",
          "license": ""
        },
        "identified": true,
        "unidentified": {
          "description": ""
        },
        "container": null,
        "quantity": 1,
        "weight": 0,
        "price": {
          "value": 0,
          "denomination": "gp"
        },
        "rarity": "",
        "attunement": 0,
        "equipped": true,
        "activation": {
          "type": "action",
          "cost": 1,
          "condition": ""
        },
        "duration": {
          "value": "",
          "units": "inst"
        },
        "cover": null,
        "crewed": false,
        "target": {
          "value": null,
          "width": null,
          "units": "",
          "type": "",
          "prompt": true
        },
        "range": {
          "value": 5,
          "long": null,
          "units": "ft"
        },
        "uses": {
          "value": null,
          "max": "",
          "per": null,
          "recovery": "",
          "prompt": true
        },
        "consume": {
          "type": "",
          "target": null,
          "amount": null,
          "scale": false
        },
        "ability": "str",
        "actionType": "mwak",
        "attack": {
          "bonus": "",
          "flat": false
        },
        "chatFlavor": "",
        "critical": {
          "threshold": null,
          "damage": ""
        },
        "damage": {
          "parts": [
            [
              "2d6[slashing] + @mod",
              "slashing"
            ],
            [
              "2d6[cold]",
              "cold"
            ]
          ],
          "versatile": ""
        },
        "formula": "",
        "save": {
          "dc": null,
          "ability": "",
          "scaling": "flat"
        },
        "summons": null,
        "armor": {
          "value": null
        },
        "hp": {
          "value": null,
          "max": null,
          "dt": null,
          "conditions": ""
        },
        "type": {
          "value": "natural",
          "baseItem": ""
        },
        "magicalBonus": null,
        "properties": [],
        "proficient": 1
      },
      "effects": [],
      "flags": {
        "ddbimporter": {
          "levelBonus": false,
          "dndbeyond": {}
        },
        "monsterMunch": {
          "titleHTML": "<strong>Claw.</strong>",
          "fullName": "Claw.",
          "actionCopy": false,
          "type": "action",
          "actionInfo": {
            "damage": {
              "parts": [
                [
                  "2d6[slashing] + @mod",
                  "slashing"
                ],
                [
                  "2d6[cold]",
                  "cold"
                ]
              ],
              "versatile": ""
            },
            "baseAbility": "str",
            "toHit": 11,
            "proficient": true,
            "extraAttackBonus": 0
          }
        },
        "midi-qol": {
          "removeAttackDamageButtons": "default"
        },
        "midiProperties": {
          "confirmTargets": "default"
        }
      },
      "img": "icons/commodities/claws/talon-red.webp",
      "folder": null,
      "sort": 0,
      "ownership": {
        "default": 0
      },
      "_stats": {
        "systemId": null,
        "systemVersion": null,
        "coreVersion": null,
        "createdTime": null,
        "modifiedTime": null,
        "lastModifiedBy": null
      },
      "_key": "!actors.items!K3sycUIZ1MXTp82C.3G0qoXERQeu7fsfd"
    },
    {
      "_id": "fhWFyP3JgW2pPSm2",
      "name": "Chilling Gaze",
      "type": "feat",
      "system": {
        "description": {
          "value": "<div class=\"ddb\">\n<section class=\"secret\">\n<p> The yeti targets one creature it can see within 30 feet of it. If the target can see the yeti, the target must succeed on a [[/save con 18 format=long]] against this magic or take [[/damage 6d6 type=cold average=true]] damage and then be &amp;Reference[paralyzed]{paralyzed} for 1 minute, unless it is immune to &amp;Reference[cold]{cold} damage. The target can repeat the saving throw at the end of each of its turns, ending the effect on itself on a success. If the target’s saving throw is successful, or if the effect ends on it, the target is immune to this yeti’s gaze for 1 hour.</p>\n</section>\nThe [[lookup @name]] uses [[lookup @item.name]] and a save is required.\n</div>",
          "chat": ""
        },
        "source": {
          "book": "Monster Manual",
          "page": "306",
          "custom": "",
          "license": ""
        },
        "activation": {
          "type": "action",
          "cost": 1,
          "condition": ""
        },
        "duration": {
          "value": "",
          "units": "inst"
        },
        "cover": null,
        "crewed": false,
        "target": {
          "value": null,
          "width": null,
          "units": "",
          "type": "",
          "prompt": true
        },
        "range": {
          "value": 30,
          "long": null,
          "units": "ft"
        },
        "uses": {
          "value": null,
          "max": "",
          "per": null,
          "recovery": "",
          "prompt": true
        },
        "consume": {
          "type": "",
          "target": null,
          "amount": null,
          "scale": false
        },
        "ability": null,
        "actionType": "save",
        "attack": {
          "bonus": "",
          "flat": false
        },
        "chatFlavor": "",
        "critical": {
          "threshold": null,
          "damage": ""
        },
        "damage": {
          "parts": [
            [
              "6d6[cold]",
              "cold"
            ]
          ],
          "versatile": ""
        },
        "formula": "",
        "save": {
          "dc": 18,
          "ability": "con",
          "scaling": "flat"
        },
        "summons": null,
        "type": {
          "value": "monster",
          "subtype": ""
        },
        "properties": [],
        "requirements": "",
        "recharge": {
          "value": null,
          "charged": false
        }
      },
      "effects": [],
      "flags": {
        "ddbimporter": {
          "levelBonus": false,
          "dndbeyond": {}
        },
        "monsterMunch": {
          "titleHTML": "<strong>Chilling Gaze.</strong>",
          "fullName": "Chilling Gaze.",
          "actionCopy": false,
          "type": "action",
          "actionInfo": {
            "damage": {
              "parts": [
                [
                  "6d6[cold]",
                  "cold"
                ]
              ],
              "versatile": ""
            },
            "baseAbility": null,
            "toHit": 0,
            "proficient": false,
            "extraAttackBonus": 0
          }
        },
        "midi-qol": {
          "removeAttackDamageButtons": "default"
        },
        "midiProperties": {
          "confirmTargets": "default"
        }
      },
      "img": "icons/magic/perception/eye-ringed-glow-angry-large-teal.webp",
      "folder": null,
      "sort": 0,
      "ownership": {
        "default": 0
      },
      "_stats": {
        "systemId": null,
        "systemVersion": null,
        "coreVersion": null,
        "createdTime": null,
        "modifiedTime": null,
        "lastModifiedBy": null
      },
      "_key": "!actors.items!K3sycUIZ1MXTp82C.fhWFyP3JgW2pPSm2"
    },
    {
      "_id": "IFWhHQbQyZY2x0Xa",
      "name": "Cold Breath",
      "type": "feat",
      "system": {
        "description": {
          "value": "<div class=\"ddb\">\n<section class=\"secret\">\n<p> The yeti exhales a 30-foot &amp;Reference[cone]{cone} of frigid air. Each creature in that area must make a [[/save con 18 format=long]], taking [[/damage 10d8 type=cold average=true]] damage on a failed save, or half as much damage on a successful one.</p>\n</section>\nThe [[lookup @name]] uses [[lookup @item.name]] and a save is required.\n</div>",
          "chat": ""
        },
        "source": {
          "book": "Monster Manual",
          "page": "306",
          "custom": "",
          "license": ""
        },
        "activation": {
          "type": "action",
          "cost": 1,
          "condition": ""
        },
        "duration": {
          "value": "",
          "units": "inst"
        },
        "cover": null,
        "crewed": false,
        "target": {
          "value": 30,
          "width": null,
          "units": "ft",
          "type": "cone",
          "prompt": true
        },
        "range": {
          "value": null,
          "long": null,
          "units": ""
        },
        "uses": {
          "value": null,
          "max": "",
          "per": null,
          "recovery": "",
          "prompt": true
        },
        "consume": {
          "type": "charges",
          "target": "IFWhHQbQyZY2x0Xa",
          "amount": null,
          "scale": false
        },
        "ability": null,
        "actionType": "save",
        "attack": {
          "bonus": "",
          "flat": false
        },
        "chatFlavor": "",
        "critical": {
          "threshold": null,
          "damage": ""
        },
        "damage": {
          "parts": [
            [
              "10d8[cold]",
              "cold"
            ]
          ],
          "versatile": ""
        },
        "formula": "",
        "save": {
          "dc": 18,
          "ability": "con",
          "scaling": "flat"
        },
        "summons": null,
        "type": {
          "value": "monster",
          "subtype": ""
        },
        "properties": [],
        "requirements": "",
        "recharge": {
          "value": 6,
          "charged": true
        }
      },
      "effects": [],
      "flags": {
        "ddbimporter": {
          "levelBonus": false,
          "dndbeyond": {}
        },
        "monsterMunch": {
          "titleHTML": "<strong>Cold Breath (Recharge 6).</strong>",
          "fullName": "Cold Breath (Recharge 6).",
          "actionCopy": false,
          "type": "action",
          "actionInfo": {
            "damage": {
              "parts": [
                [
                  "10d8[cold]",
                  "cold"
                ]
              ],
              "versatile": ""
            },
            "baseAbility": null,
            "toHit": 0,
            "proficient": false,
            "extraAttackBonus": 0
          }
        },
        "midiProperties": {
          "halfdam": true,
          "saveDamage": "halfdam",
          "confirmTargets": "default"
        },
        "midi-qol": {
          "removeAttackDamageButtons": "default"
        }
      },
      "img": "icons/magic/air/fog-gas-smoke-dense-blue.webp",
      "folder": null,
      "sort": 0,
      "ownership": {
        "default": 0
      },
      "_stats": {
        "systemId": null,
        "systemVersion": null,
        "coreVersion": null,
        "createdTime": null,
        "modifiedTime": null,
        "lastModifiedBy": null
      },
      "_key": "!actors.items!K3sycUIZ1MXTp82C.IFWhHQbQyZY2x0Xa"
    },
    {
      "_id": "KkxxJBFAQku7qPVQ",
      "name": "Fear of Fire",
      "type": "feat",
      "system": {
        "description": {
          "value": "<div class=\"ddb\">\n<section class=\"secret\">\n<p><em><strong>Fear of &amp;Reference[fire]{Fire}.</strong></em> If the yeti takes &amp;Reference[fire]{fire} damage, it has disadvantage on attack rolls and ability checks until the end of its next turn.</p>\n</section>\nThe [[lookup @name]] uses [[lookup @item.name]].\n</div>",
          "chat": ""
        },
        "source": {
          "book": "Monster Manual",
          "page": "306",
          "custom": "",
          "license": ""
        },
        "activation": {
          "cost": null,
          "type": "",
          "condition": ""
        },
        "duration": {
          "value": "",
          "units": ""
        },
        "cover": null,
        "crewed": false,
        "target": {
          "value": null,
          "width": null,
          "units": "",
          "type": "",
          "prompt": true
        },
        "range": {
          "value": null,
          "long": null,
          "units": ""
        },
        "uses": {
          "value": null,
          "max": "",
          "per": null,
          "recovery": "",
          "prompt": true
        },
        "consume": {
          "type": "",
          "target": null,
          "amount": null,
          "scale": false
        },
        "ability": null,
        "actionType": null,
        "attack": {
          "bonus": "",
          "flat": false
        },
        "chatFlavor": "",
        "critical": {
          "threshold": null,
          "damage": ""
        },
        "damage": {
          "parts": [],
          "versatile": ""
        },
        "formula": "",
        "save": {
          "dc": null,
          "ability": "",
          "scaling": "flat"
        },
        "summons": null,
        "type": {
          "value": "monster",
          "subtype": ""
        },
        "properties": [],
        "requirements": "",
        "recharge": {
          "value": null,
          "charged": false
        }
      },
      "effects": [],
      "flags": {
        "ddbimporter": {
          "levelBonus": false,
          "dndbeyond": {}
        },
        "monsterMunch": {
          "titleHTML": "<em><strong>Fear of Fire.</strong></em>",
          "fullName": "Fear of Fire.",
          "actionCopy": false,
          "type": "special",
          "actionInfo": {
            "damage": {
              "parts": [],
              "versatile": ""
            },
            "baseAbility": null,
            "toHit": 0,
            "proficient": false,
            "extraAttackBonus": 0
          }
        },
        "midi-qol": {
          "removeAttackDamageButtons": "default"
        },
        "midiProperties": {
          "confirmTargets": "default"
        }
      },
      "img": "icons/magic/fire/explosion-embers-evade-silhouette.webp",
      "folder": null,
      "sort": 0,
      "ownership": {
        "default": 0
      },
      "_stats": {
        "systemId": null,
        "systemVersion": null,
        "coreVersion": null,
        "createdTime": null,
        "modifiedTime": null,
        "lastModifiedBy": null
      },
      "_key": "!actors.items!K3sycUIZ1MXTp82C.KkxxJBFAQku7qPVQ"
    },
    {
      "_id": "bzIg0xcOcdhcWI5U",
      "name": "Keen Smell",
      "type": "feat",
      "system": {
        "description": {
          "value": "<div class=\"ddb\">\n<section class=\"secret\">\n<p><em><strong>Keen Smell.</strong></em> The yeti has advantage on &amp;Reference[wis]{Wisdom} (&amp;Reference[prc]{Perception}) checks that rely on smell.</p>\n</section>\nThe [[lookup @name]] uses [[lookup @item.name]].\n</div>",
          "chat": ""
        },
        "source": {
          "book": "Monster Manual",
          "page": "306",
          "custom": "",
          "license": ""
        },
        "activation": {
          "cost": null,
          "type": "",
          "condition": ""
        },
        "duration": {
          "value": "",
          "units": ""
        },
        "cover": null,
        "crewed": false,
        "target": {
          "value": null,
          "width": null,
          "units": "",
          "type": "",
          "prompt": true
        },
        "range": {
          "value": null,
          "long": null,
          "units": ""
        },
        "uses": {
          "value": null,
          "max": "",
          "per": null,
          "recovery": "",
          "prompt": true
        },
        "consume": {
          "type": "",
          "target": null,
          "amount": null,
          "scale": false
        },
        "ability": null,
        "actionType": null,
        "attack": {
          "bonus": "",
          "flat": false
        },
        "chatFlavor": "",
        "critical": {
          "threshold": null,
          "damage": ""
        },
        "damage": {
          "parts": [],
          "versatile": ""
        },
        "formula": "",
        "save": {
          "dc": null,
          "ability": "",
          "scaling": "flat"
        },
        "summons": null,
        "type": {
          "value": "monster",
          "subtype": ""
        },
        "properties": [],
        "requirements": "",
        "recharge": {
          "value": null,
          "charged": false
        }
      },
      "effects": [],
      "flags": {
        "ddbimporter": {
          "levelBonus": false,
          "dndbeyond": {}
        },
        "monsterMunch": {
          "titleHTML": "<em><strong>Keen Smell.</strong></em>",
          "fullName": "Keen Smell.",
          "actionCopy": false,
          "type": "special",
          "actionInfo": {
            "damage": {
              "parts": [],
              "versatile": ""
            },
            "baseAbility": null,
            "toHit": 0,
            "proficient": false,
            "extraAttackBonus": 0
          }
        },
        "midi-qol": {
          "removeAttackDamageButtons": "default"
        },
        "midiProperties": {
          "confirmTargets": "default"
        }
      },
      "img": "icons/commodities/tech/smoke-bomb-red-yellow.webp",
      "folder": null,
      "sort": 0,
      "ownership": {
        "default": 0
      },
      "_stats": {
        "systemId": null,
        "systemVersion": null,
        "coreVersion": null,
        "createdTime": null,
        "modifiedTime": null,
        "lastModifiedBy": null
      },
      "_key": "!actors.items!K3sycUIZ1MXTp82C.bzIg0xcOcdhcWI5U"
    },
    {
      "_id": "Jfi68TQAVOXyjaTE",
      "name": "Snow Camouflage",
      "type": "feat",
      "system": {
        "description": {
          "value": "<div class=\"ddb\">\n<section class=\"secret\">\n<p><em><strong>Snow Camouflage.</strong></em> The yeti has advantage on &amp;Reference[dex]{Dexterity} (&amp;Reference[ste]{Stealth}) checks made to hide in snowy terrain.</p>\n</section>\nThe [[lookup @name]] uses [[lookup @item.name]].\n</div>",
          "chat": ""
        },
        "source": {
          "book": "Monster Manual",
          "page": "306",
          "custom": "",
          "license": ""
        },
        "activation": {
          "cost": null,
          "type": "",
          "condition": ""
        },
        "duration": {
          "value": "",
          "units": ""
        },
        "cover": null,
        "crewed": false,
        "target": {
          "value": null,
          "width": null,
          "units": "",
          "type": "",
          "prompt": true
        },
        "range": {
          "value": null,
          "long": null,
          "units": ""
        },
        "uses": {
          "value": null,
          "max": "",
          "per": null,
          "recovery": "",
          "prompt": true
        },
        "consume": {
          "type": "",
          "target": null,
          "amount": null,
          "scale": false
        },
        "ability": null,
        "actionType": null,
        "attack": {
          "bonus": "",
          "flat": false
        },
        "chatFlavor": "",
        "critical": {
          "threshold": null,
          "damage": ""
        },
        "damage": {
          "parts": [],
          "versatile": ""
        },
        "formula": "",
        "save": {
          "dc": null,
          "ability": "",
          "scaling": "flat"
        },
        "summons": null,
        "type": {
          "value": "monster",
          "subtype": ""
        },
        "properties": [],
        "requirements": "",
        "recharge": {
          "value": null,
          "charged": false
        }
      },
      "effects": [],
      "flags": {
        "ddbimporter": {
          "levelBonus": false,
          "dndbeyond": {}
        },
        "monsterMunch": {
          "titleHTML": "<em><strong>Snow Camouflage.</strong></em>",
          "fullName": "Snow Camouflage.",
          "actionCopy": false,
          "type": "special",
          "actionInfo": {
            "damage": {
              "parts": [],
              "versatile": ""
            },
            "baseAbility": null,
            "toHit": 0,
            "proficient": false,
            "extraAttackBonus": 0
          }
        },
        "midi-qol": {
          "removeAttackDamageButtons": "default"
        },
        "midiProperties": {
          "confirmTargets": "default"
        }
      },
      "img": "icons/magic/air/air-wave-gust-blue.webp",
      "folder": null,
      "sort": 0,
      "ownership": {
        "default": 0
      },
      "_stats": {
        "systemId": null,
        "systemVersion": null,
        "coreVersion": null,
        "createdTime": null,
        "modifiedTime": null,
        "lastModifiedBy": null
      },
      "_key": "!actors.items!K3sycUIZ1MXTp82C.Jfi68TQAVOXyjaTE"
    }
  ],
  "effects": [],
  "folder": "OdQClMm2HO5KTQjz",
  "sort": 0,
  "ownership": {
    "default": 0,
    "6yhz13iFYYklKtgA": 3
  },
  "flags": {
    "dnd5e": {},
    "monsterMunch": {
      "url": "https://www.dndbeyond.com/monsters/17105-abominable-yeti",
      "img": "https://www.dndbeyond.com/avatars/4675/676/636747837839875603.jpeg",
      "tokenImg": "https://www.dndbeyond.com/avatars/4675/676/636747837839875603.jpeg",
      "isStockImg": true,
      "spellList": {
        "class": [],
        "pact": [],
        "atwill": [],
        "innate": [],
        "edgeCases": [],
        "material": true,
        "innateMatch": false
      }
    },
    "ddbimporter": {
      "id": 17105,
      "entityTypeId": 779871897,
      "creatureGroupId": null,
      "creatureFlags": [],
      "version": "5.1.27",
      "isLegacy": false,
      "flatAC": false
    }
  },
  "_stats": {
    "systemId": "dnd5e",
    "systemVersion": "3.1.2",
    "coreVersion": "11.315",
    "createdTime": 1721275216868,
    "modifiedTime": 1721275216868,
    "lastModifiedBy": "6yhz13iFYYklKtgA"
  },
  "_key": "!actors!K3sycUIZ1MXTp82C"
}
