{
  "name": "Giant Lightning Eel",
  "type": "npc",
  "_id": "8ooSMykLkZsMG0Du",
  "img": "https://www.dndbeyond.com/avatars/4675/664/636747837303835953.jpeg",
  "system": {
    "currency": {
      "pp": 0,
      "gp": 0,
      "ep": 0,
      "sp": 0,
      "cp": 0
    },
    "abilities": {
      "str": {
        "value": 11,
        "proficient": 0,
        "max": null,
        "bonuses": {
          "check": "",
          "save": ""
        },
        "check": {
          "roll": {
            "min": null,
            "max": null,
            "mode": 0
          }
        },
        "save": {
          "roll": {
            "min": null,
            "max": null,
            "mode": 0
          }
        }
      },
      "dex": {
        "value": 17,
        "proficient": 0,
        "max": null,
        "bonuses": {
          "check": "",
          "save": ""
        },
        "check": {
          "roll": {
            "min": null,
            "max": null,
            "mode": 0
          }
        },
        "save": {
          "roll": {
            "min": null,
            "max": null,
            "mode": 0
          }
        }
      },
      "con": {
        "value": 16,
        "proficient": 0,
        "max": null,
        "bonuses": {
          "check": "",
          "save": ""
        },
        "check": {
          "roll": {
            "min": null,
            "max": null,
            "mode": 0
          }
        },
        "save": {
          "roll": {
            "min": null,
            "max": null,
            "mode": 0
          }
        }
      },
      "int": {
        "value": 2,
        "proficient": 0,
        "max": null,
        "bonuses": {
          "check": "",
          "save": ""
        },
        "check": {
          "roll": {
            "min": null,
            "max": null,
            "mode": 0
          }
        },
        "save": {
          "roll": {
            "min": null,
            "max": null,
            "mode": 0
          }
        }
      },
      "wis": {
        "value": 12,
        "proficient": 0,
        "max": null,
        "bonuses": {
          "check": "",
          "save": ""
        },
        "check": {
          "roll": {
            "min": null,
            "max": null,
            "mode": 0
          }
        },
        "save": {
          "roll": {
            "min": null,
            "max": null,
            "mode": 0
          }
        }
      },
      "cha": {
        "value": 3,
        "proficient": 0,
        "max": null,
        "bonuses": {
          "check": "",
          "save": ""
        },
        "check": {
          "roll": {
            "min": null,
            "max": null,
            "mode": 0
          }
        },
        "save": {
          "roll": {
            "min": null,
            "max": null,
            "mode": 0
          }
        }
      }
    },
    "bonuses": {
      "mwak": {
        "attack": "",
        "damage": ""
      },
      "rwak": {
        "attack": "",
        "damage": ""
      },
      "msak": {
        "attack": "",
        "damage": ""
      },
      "rsak": {
        "attack": "",
        "damage": ""
      },
      "abilities": {
        "check": "",
        "save": "",
        "skill": ""
      },
      "spell": {
        "dc": ""
      }
    },
    "skills": {
      "acr": {
        "ability": "dex",
        "roll": {
          "min": null,
          "max": null,
          "mode": 0
        },
        "value": 0,
        "bonuses": {
          "check": "",
          "passive": ""
        }
      },
      "ani": {
        "ability": "wis",
        "roll": {
          "min": null,
          "max": null,
          "mode": 0
        },
        "value": 0,
        "bonuses": {
          "check": "",
          "passive": ""
        }
      },
      "arc": {
        "ability": "int",
        "roll": {
          "min": null,
          "max": null,
          "mode": 0
        },
        "value": 0,
        "bonuses": {
          "check": "",
          "passive": ""
        }
      },
      "ath": {
        "ability": "str",
        "roll": {
          "min": null,
          "max": null,
          "mode": 0
        },
        "value": 0,
        "bonuses": {
          "check": "",
          "passive": ""
        }
      },
      "dec": {
        "ability": "cha",
        "roll": {
          "min": null,
          "max": null,
          "mode": 0
        },
        "value": 0,
        "bonuses": {
          "check": "",
          "passive": ""
        }
      },
      "his": {
        "ability": "int",
        "roll": {
          "min": null,
          "max": null,
          "mode": 0
        },
        "value": 0,
        "bonuses": {
          "check": "",
          "passive": ""
        }
      },
      "ins": {
        "ability": "wis",
        "roll": {
          "min": null,
          "max": null,
          "mode": 0
        },
        "value": 0,
        "bonuses": {
          "check": "",
          "passive": ""
        }
      },
      "itm": {
        "ability": "cha",
        "roll": {
          "min": null,
          "max": null,
          "mode": 0
        },
        "value": 0,
        "bonuses": {
          "check": "",
          "passive": ""
        }
      },
      "inv": {
        "ability": "int",
        "roll": {
          "min": null,
          "max": null,
          "mode": 0
        },
        "value": 0,
        "bonuses": {
          "check": "",
          "passive": ""
        }
      },
      "med": {
        "ability": "wis",
        "roll": {
          "min": null,
          "max": null,
          "mode": 0
        },
        "value": 0,
        "bonuses": {
          "check": "",
          "passive": ""
        }
      },
      "nat": {
        "ability": "int",
        "roll": {
          "min": null,
          "max": null,
          "mode": 0
        },
        "value": 0,
        "bonuses": {
          "check": "",
          "passive": ""
        }
      },
      "prc": {
        "ability": "wis",
        "roll": {
          "min": null,
          "max": null,
          "mode": 0
        },
        "value": 0,
        "bonuses": {
          "check": "",
          "passive": ""
        }
      },
      "prf": {
        "ability": "cha",
        "roll": {
          "min": null,
          "max": null,
          "mode": 0
        },
        "value": 0,
        "bonuses": {
          "check": "",
          "passive": ""
        }
      },
      "per": {
        "ability": "cha",
        "roll": {
          "min": null,
          "max": null,
          "mode": 0
        },
        "value": 0,
        "bonuses": {
          "check": "",
          "passive": ""
        }
      },
      "rel": {
        "ability": "int",
        "roll": {
          "min": null,
          "max": null,
          "mode": 0
        },
        "value": 0,
        "bonuses": {
          "check": "",
          "passive": ""
        }
      },
      "slt": {
        "ability": "dex",
        "roll": {
          "min": null,
          "max": null,
          "mode": 0
        },
        "value": 0,
        "bonuses": {
          "check": "",
          "passive": ""
        }
      },
      "ste": {
        "ability": "dex",
        "roll": {
          "min": null,
          "max": null,
          "mode": 0
        },
        "value": 0,
        "bonuses": {
          "check": "",
          "passive": ""
        }
      },
      "sur": {
        "ability": "wis",
        "roll": {
          "min": null,
          "max": null,
          "mode": 0
        },
        "value": 0,
        "bonuses": {
          "check": "",
          "passive": ""
        }
      }
    },
    "tools": {},
    "spells": {
      "spell1": {
        "value": 0,
        "override": null
      },
      "spell2": {
        "value": 0,
        "override": null
      },
      "spell3": {
        "value": 0,
        "override": null
      },
      "spell4": {
        "value": 0,
        "override": null
      },
      "spell5": {
        "value": 0,
        "override": null
      },
      "spell6": {
        "value": 0,
        "override": null
      },
      "spell7": {
        "value": 0,
        "override": null
      },
      "spell8": {
        "value": 0,
        "override": null
      },
      "spell9": {
        "value": 0,
        "override": null
      },
      "pact": {
        "value": 0,
        "override": null
      }
    },
    "attributes": {
      "init": {
        "ability": "",
        "roll": {
          "min": null,
          "max": null,
          "mode": 0
        },
        "bonus": ""
      },
      "movement": {
        "burrow": null,
        "climb": null,
        "fly": null,
        "swim": 30,
        "walk": 5,
        "units": "ft",
        "hover": false
      },
      "attunement": {
        "max": 3
      },
      "senses": {
        "darkvision": 0,
        "blindsight": 60,
        "tremorsense": 0,
        "truesight": 0,
        "units": "ft",
        "special": ""
      },
      "spellcasting": "int",
      "exhaustion": 0,
      "concentration": {
        "ability": "",
        "roll": {
          "min": null,
          "max": null,
          "mode": 0
        },
        "bonuses": {
          "save": ""
        },
        "limit": 1
      },
      "ac": {
        "flat": 13,
        "calc": "natural",
        "formula": ""
      },
      "hp": {
        "value": 42,
        "max": 42,
        "temp": 0,
        "tempmax": 0,
        "formula": "5d10 + 15"
      },
      "death": {
        "ability": "",
        "roll": {
          "min": null,
          "max": null,
          "mode": 0
        },
        "success": 0,
        "failure": 0,
        "bonuses": {
          "save": ""
        }
      },
      "spell": {
        "level": 0
      },
      "loyalty": {
        "value": null
      },
      "hd": {
        "spent": 0
      }
    },
    "details": {
      "biography": {
        "value": "",
        "public": ""
      },
      "alignment": "Unaligned",
      "race": null,
      "type": {
        "value": "beast",
        "subtype": ""
      },
      "environment": "",
      "cr": 3,
      "spellLevel": 0,
      "source": {
        "book": "Tales from the Yawning Portal",
        "custom": "",
        "license": ""
      },
      "habitat": {
        "custom": "",
        "value": []
      },
      "ideal": "",
      "bond": "",
      "flaw": "",
      "treasure": {
        "value": []
      }
    },
    "resources": {
      "legact": {
        "value": 0,
        "max": 0
      },
      "legres": {
        "value": 0,
        "max": 0
      },
      "lair": {
        "value": false,
        "initiative": null,
        "inside": false
      }
    },
    "traits": {
      "size": "lg",
      "di": {
        "value": [],
        "bypasses": [],
        "custom": ""
      },
      "dr": {
        "value": [
          "lightning"
        ],
        "bypasses": [],
        "custom": ""
      },
      "dv": {
        "value": [],
        "bypasses": [],
        "custom": ""
      },
      "dm": {
        "amount": {},
        "bypasses": []
      },
      "ci": {
        "value": [],
        "custom": ""
      },
      "languages": {
        "value": [],
        "custom": "",
        "communication": {}
      },
      "important": false
    },
    "source": {
      "book": "Tales from the Yawning Portal",
      "custom": "",
      "license": "",
      "revision": 1,
      "rules": "2014"
    }
  },
  "prototypeToken": {
    "name": "Giant Lightning Eel",
    "displayName": 20,
    "actorLink": false,
    "appendNumber": false,
    "prependAdjective": false,
    "texture": {
      "src": "ddb-images/other/npc-generic-token-beast.jpeg",
      "scaleX": 1,
      "scaleY": 1,
      "offsetX": 0,
      "offsetY": 0,
      "rotation": 0,
      "anchorX": 0.5,
      "anchorY": 0.5,
      "fit": "contain",
      "tint": "#ffffff",
      "alphaThreshold": 0.75
    },
    "width": 2,
    "height": 2,
    "lockRotation": false,
    "rotation": 0,
    "alpha": 1,
    "disposition": -1,
    "displayBars": 20,
    "bar1": {
      "attribute": "attributes.hp"
    },
    "bar2": {
      "attribute": null
    },
    "light": {
      "alpha": 0.5,
      "angle": 360,
      "bright": 0,
      "coloration": 1,
      "dim": 0,
      "attenuation": 0.5,
      "luminosity": 0.5,
      "saturation": 0,
      "contrast": 0,
      "shadows": 0,
      "animation": {
        "type": null,
        "speed": 5,
        "intensity": 5,
        "reverse": false
      },
      "darkness": {
        "min": 0,
        "max": 1
      },
      "negative": false,
      "priority": 0,
      "color": null
    },
    "sight": {
      "enabled": false,
      "range": 60,
      "angle": 360,
      "visionMode": "basic",
      "color": null,
      "attenuation": 0,
      "brightness": 0,
      "saturation": 0,
      "contrast": 0
    },
    "detectionModes": [
      {
        "id": "senseAll",
        "range": 60,
        "enabled": true
      }
    ],
    "flags": {
      "monks-tokenbar": {
        "include": "default"
      },
      "tagger": {
        "tags": [
          "dndbeyond",
          "ddb-importer",
          "beast"
        ]
      }
    },
    "randomImg": false,
    "hexagonalShape": 1,
    "occludable": {
      "radius": 0
    },
    "ring": {
      "enabled": false,
      "colors": {
        "ring": null,
        "background": null
      },
      "effects": 1,
      "subject": {
        "scale": 1,
        "texture": null
      }
    }
  },
  "items": [
    {
      "_id": "h6w7DC17yReuhHSt",
      "name": "Multiattack",
      "type": "feat",
      "system": {
        "description": {
          "value": "<div class=\"ddb\">\n<section class=\"secret\">\n<p> The eel makes two bite attacks.</p>\n</section>\nThe [[lookup @name]] uses [[lookup @item.name]].\n</div>",
          "chat": ""
        },
        "source": {
          "book": "Tales from the Yawning Portal",
          "custom": "",
          "license": "",
          "revision": 1,
          "rules": "2024"
        },
        "activation": {
          "type": "action",
          "cost": 1,
          "condition": ""
        },
        "duration": {
          "value": "",
          "units": "inst"
        },
        "cover": null,
        "crewed": false,
        "target": {
          "value": null,
          "width": null,
          "units": "",
          "type": "",
          "prompt": true
        },
        "range": {
          "value": null,
          "long": null,
          "units": ""
        },
        "uses": {
          "value": null,
          "max": "",
          "per": null,
          "recovery": [],
          "prompt": true,
          "spent": 0
        },
        "consume": {
          "type": "",
          "target": null,
          "amount": null,
          "scale": false
        },
        "ability": null,
        "actionType": null,
        "attack": {
          "bonus": "",
          "flat": false
        },
        "chatFlavor": "",
        "critical": {
          "threshold": null,
          "damage": ""
        },
        "damage": {
          "parts": [],
          "versatile": ""
        },
        "formula": "",
        "save": {
          "dc": null,
          "ability": "",
          "scaling": "flat"
        },
        "summons": null,
        "type": {
          "value": "monster",
          "subtype": ""
        },
        "properties": [],
        "requirements": "",
        "recharge": {
          "value": null,
          "charged": false
        },
        "activities": {
          "dnd5eactivity000": {
            "_id": "dnd5eactivity000",
            "type": "utility",
            "activation": {
              "type": "action",
              "value": 1,
              "condition": "",
              "override": false
            },
            "consumption": {
              "targets": [],
              "scaling": {
                "allowed": false,
                "max": ""
              },
              "spellSlot": true
            },
            "description": {
              "chatFlavor": ""
            },
            "duration": {
              "concentration": false,
              "value": "",
              "units": "inst",
              "special": "",
              "override": false
            },
            "effects": [],
            "range": {
              "units": "",
              "special": "",
              "override": false
            },
            "target": {
              "template": {
                "count": "",
                "contiguous": false,
                "type": "",
                "size": "",
                "width": "",
                "height": "",
                "units": ""
              },
              "affects": {
                "count": "",
                "type": "",
                "choice": false,
                "special": ""
              },
              "prompt": true,
              "override": false
            },
            "uses": {
              "spent": 0,
              "max": "",
              "recovery": []
            },
            "roll": {
              "formula": "",
              "name": "",
              "prompt": false,
              "visible": false
            },
            "sort": 0,
            "useConditionText": "",
            "useConditionReason": "",
            "effectConditionText": "",
            "macroData": {
              "name": "",
              "command": ""
            },
            "ignoreTraits": {
              "idi": false,
              "idr": false,
              "idv": false,
              "ida": false
            },
            "midiProperties": {
              "ignoreTraits": [],
              "triggeredActivityId": "none",
              "triggeredActivityConditionText": "",
              "triggeredActivityTargets": "targets",
              "triggeredActivityRollAs": "self",
              "forceDialog": false,
              "confirmTargets": "default",
              "autoTargetType": "any",
              "autoTargetAction": "default",
              "automationOnly": false,
              "otherActivityCompatible": true,
              "identifier": "",
              "displayActivityName": false,
              "rollMode": "default",
              "chooseEffects": false,
              "toggleEffect": false,
              "ignoreFullCover": false
            },
            "isOverTimeFlag": false,
            "overTimeProperties": {
              "saveRemoves": true,
              "preRemoveConditionText": "",
              "postRemoveConditionText": ""
            },
            "otherActivityId": "none"
          }
        },
        "identifier": "",
        "advancement": [],
        "enchant": {},
        "prerequisites": {
          "level": null,
          "repeatable": false
        }
      },
      "effects": [],
      "flags": {
        "ddbimporter": {
          "levelBonus": false,
          "dndbeyond": {}
        },
        "monsterMunch": {
          "titleHTML": "<strong>Multiattack.</strong>",
          "fullName": "Multiattack.",
          "actionCopy": false,
          "type": "action",
          "actionInfo": {
            "damage": {
              "parts": [],
              "versatile": ""
            },
            "baseAbility": null,
            "toHit": 0,
            "proficient": false,
            "extraAttackBonus": 0
          }
        },
        "midi-qol": {
          "removeAttackDamageButtons": "default"
        },
        "midiProperties": {
          "confirmTargets": "default"
        },
        "dnd5e": {}
      },
      "img": "icons/skills/melee/strike-weapons-orange.webp",
      "folder": null,
      "sort": 0,
      "ownership": {
        "default": 0
      },
      "_stats": {
        "systemId": null,
        "systemVersion": null,
        "coreVersion": "12.331",
        "createdTime": null,
        "modifiedTime": null,
        "lastModifiedBy": null,
        "compendiumSource": null,
        "duplicateSource": null
      },
      "_key": "!actors.items!8ooSMykLkZsMG0Du.h6w7DC17yReuhHSt"
    },
    {
      "_id": "6jmk9B5kPNDhWubh",
      "name": "Bite",
      "type": "weapon",
      "system": {
        "description": {
          "value": "<div class=\"ddb\">\n<section class=\"secret\">\n<p><em><strong></strong> Melee Weapon Attack:</em> +5 to hit, reach 5 ft., one target. <em>Hit:</em> [[/damage 2d6 + @mod type=piercing average=true]] damage plus [[/damage 1d8 type=lightning average=true]] damage.</p>\n</section>\nThe [[lookup @name]] attacks with its [[lookup @item.name]].\n</div>",
          "chat": ""
        },
        "source": {
          "book": "Tales from the Yawning Portal",
          "custom": "",
          "license": "",
          "revision": 1,
          "rules": "2024"
        },
        "identified": true,
        "unidentified": {
          "description": ""
        },
        "container": null,
        "quantity": 1,
        "weight": {
          "value": 0,
          "units": "lb"
        },
        "price": {
          "value": 0,
          "denomination": "gp"
        },
        "rarity": "",
        "attunement": "",
        "equipped": true,
        "activation": {
          "type": "action",
          "cost": 1,
          "condition": ""
        },
        "duration": {
          "value": "",
          "units": "inst"
        },
        "cover": null,
        "crewed": false,
        "target": {
          "value": null,
          "width": null,
          "units": "",
          "type": "",
          "prompt": true
        },
        "range": {
          "value": 5,
          "long": null,
          "units": "ft",
          "reach": null
        },
        "uses": {
          "value": null,
          "max": "",
          "per": null,
          "recovery": [],
          "prompt": true,
          "spent": 0
        },
        "consume": {
          "type": "",
          "target": null,
          "amount": null,
          "scale": false
        },
        "ability": "dex",
        "actionType": "mwak",
        "attack": {
          "bonus": "",
          "flat": false
        },
        "chatFlavor": "",
        "critical": {
          "threshold": null,
          "damage": ""
        },
        "damage": {
          "parts": [
            [
              "2d6[piercing] + @mod",
              "piercing"
            ],
            [
              "1d8[lightning]",
              "lightning"
            ]
          ],
          "versatile": {
            "number": null,
            "denomination": null,
            "bonus": "",
            "types": [],
            "custom": {
              "enabled": false,
              "formula": ""
            },
            "scaling": {
              "mode": "",
              "number": null,
              "formula": ""
            }
          },
          "base": {
            "number": null,
            "denomination": null,
            "bonus": "",
            "types": [
              "piercing"
            ],
            "custom": {
              "enabled": true,
              "formula": "2d6[piercing] + @mod"
            },
            "scaling": {
              "mode": "",
              "number": null,
              "formula": ""
            }
          }
        },
        "formula": "",
        "save": {
          "dc": null,
          "ability": "",
          "scaling": "flat"
        },
        "summons": null,
        "armor": {
          "value": null
        },
        "hp": {
          "value": null,
          "max": null,
          "dt": null,
          "conditions": ""
        },
        "type": {
          "value": "natural",
          "baseItem": ""
        },
        "magicalBonus": null,
        "properties": [],
        "proficient": 1,
        "activities": {
          "dnd5eactivity000": {
            "_id": "dnd5eactivity000",
            "type": "attack",
            "activation": {
              "type": "action",
              "value": 1,
              "condition": "",
              "override": false
            },
            "consumption": {
              "targets": [],
              "scaling": {
                "allowed": false,
                "max": ""
              },
              "spellSlot": true
            },
            "description": {
              "chatFlavor": ""
            },
            "duration": {
              "concentration": false,
              "value": "",
              "units": "inst",
              "special": "",
              "override": false
            },
            "effects": [],
            "range": {
              "value": "5",
              "units": "ft",
              "special": "",
              "override": false
            },
            "target": {
              "template": {
                "count": "",
                "contiguous": false,
                "type": "",
                "size": "",
                "width": "",
                "height": "",
                "units": ""
              },
              "affects": {
                "count": "",
                "type": "",
                "choice": false,
                "special": ""
              },
              "prompt": true,
              "override": false
            },
            "uses": {
              "spent": 0,
              "max": "",
              "recovery": []
            },
            "attack": {
              "ability": "dex",
              "bonus": "",
              "critical": {
                "threshold": null
              },
              "flat": false,
              "type": {
                "value": "melee",
                "classification": "weapon"
              }
            },
            "damage": {
              "critical": {
                "bonus": ""
              },
              "includeBase": true,
              "parts": [
                {
                  "number": null,
                  "denomination": null,
                  "bonus": "",
                  "types": [
                    "lightning"
                  ],
                  "custom": {
                    "enabled": true,
                    "formula": "1d8[lightning]"
                  },
                  "scaling": {
                    "mode": "whole",
                    "number": null,
                    "formula": ""
                  }
                }
              ]
            },
            "sort": 0,
            "useConditionText": "",
            "useConditionReason": "",
            "effectConditionText": "",
            "macroData": {
              "name": "",
              "command": ""
            },
            "ignoreTraits": {
              "idi": false,
              "idr": false,
              "idv": false,
              "ida": false
            },
            "midiProperties": {
              "ignoreTraits": [],
              "triggeredActivityId": "none",
              "triggeredActivityConditionText": "",
              "triggeredActivityTargets": "targets",
              "triggeredActivityRollAs": "self",
              "forceDialog": false,
              "confirmTargets": "default",
              "autoTargetType": "any",
              "autoTargetAction": "default",
              "automationOnly": false,
              "otherActivityCompatible": true,
              "identifier": "",
              "displayActivityName": false,
              "rollMode": "default",
              "chooseEffects": false,
              "toggleEffect": false,
              "ignoreFullCover": false
            },
            "isOverTimeFlag": false,
            "overTimeProperties": {
              "saveRemoves": true,
              "preRemoveConditionText": "",
              "postRemoveConditionText": ""
            },
            "otherActivityId": "",
            "attackMode": "oneHanded",
            "ammunition": "",
            "otherActivityUuid": ""
          }
        },
        "identifier": "",
        "attuned": false,
        "ammunition": {}
      },
      "effects": [],
      "flags": {
        "ddbimporter": {
          "levelBonus": false,
          "dndbeyond": {}
        },
        "monsterMunch": {
          "titleHTML": "<strong>Bite.</strong>",
          "fullName": "Bite.",
          "actionCopy": false,
          "type": "action",
          "actionInfo": {
            "damage": {
              "parts": [
                [
                  "2d6[piercing] + @mod",
                  "piercing"
                ],
                [
                  "1d8[lightning]",
                  "lightning"
                ]
              ],
              "versatile": ""
            },
            "baseAbility": "dex",
            "toHit": 5,
            "proficient": true,
            "extraAttackBonus": 0
          }
        },
        "midi-qol": {
          "removeAttackDamageButtons": "default"
        },
        "midiProperties": {
          "confirmTargets": "default"
        },
        "dnd5e": {}
      },
      "img": "icons/creatures/abilities/mouth-teeth-long-red.webp",
      "folder": null,
      "sort": 0,
      "ownership": {
        "default": 0
      },
      "_stats": {
        "systemId": null,
        "systemVersion": null,
        "coreVersion": "12.331",
        "createdTime": null,
        "modifiedTime": null,
        "lastModifiedBy": null,
        "compendiumSource": null,
        "duplicateSource": null
      },
      "_key": "!actors.items!8ooSMykLkZsMG0Du.6jmk9B5kPNDhWubh"
    },
    {
      "_id": "cybSoIVrQZ4iOyzk",
      "name": "Lightning Jolt",
      "type": "feat",
      "system": {
        "description": {
          "value": "<div class=\"ddb\">\n<section class=\"secret\">\n<p> One creature the eel touches within 5 feet of it outside water, or each creature within 15 feet of it in a body of water, must make a [[/save con 12 format=long]]. On failed save, a target takes [[/damage 3d8 type=lightning average=true]] damage. If the target takes any of this damage, the target is &amp;Reference[stunned]{stunned} until the end of the eel’s next turn. On a successful save, a target takes half as much damage and isn’t &amp;Reference[stunned]{stunned}.</p>\n</section>\nThe [[lookup @name]] uses [[lookup @item.name]] and a save is required.\n</div>",
          "chat": ""
        },
        "source": {
          "book": "Tales from the Yawning Portal",
          "custom": "",
          "license": "",
          "revision": 1,
          "rules": "2024"
        },
        "activation": {
          "type": "action",
          "cost": 1,
          "condition": ""
        },
        "duration": {
          "value": "",
          "units": "inst"
        },
        "cover": null,
        "crewed": false,
        "target": {
          "value": null,
          "width": null,
          "units": "",
          "type": "",
          "prompt": true
        },
        "range": {
          "value": 5,
          "long": null,
          "units": "ft"
        },
        "uses": {
          "value": null,
          "max": "1",
          "per": null,
          "recovery": [
            {
              "period": "recharge",
              "formula": "5",
              "type": "recoverAll"
            }
          ],
          "prompt": true,
          "spent": 0
        },
        "consume": {
          "type": "charges",
          "target": "cybSoIVrQZ4iOyzk",
          "amount": null,
          "scale": false
        },
        "ability": null,
        "actionType": "save",
        "attack": {
          "bonus": "",
          "flat": false
        },
        "chatFlavor": "",
        "critical": {
          "threshold": null,
          "damage": ""
        },
        "damage": {
          "parts": [
            [
              "3d8[lightning]",
              "lightning"
            ]
          ],
          "versatile": ""
        },
        "formula": "",
        "save": {
          "dc": 12,
          "ability": "con",
          "scaling": "flat"
        },
        "summons": null,
        "type": {
          "value": "monster",
          "subtype": ""
        },
        "properties": [],
        "requirements": "",
        "recharge": {
          "value": 5,
          "charged": true
        },
        "activities": {
          "dnd5eactivity000": {
            "_id": "dnd5eactivity000",
            "type": "save",
            "activation": {
              "type": "action",
              "value": 1,
              "condition": "",
              "override": false
            },
            "consumption": {
              "targets": [
                {
                  "type": "itemUses",
                  "target": "cybSoIVrQZ4iOyzk",
                  "value": "1",
                  "scaling": {
                    "mode": "",
                    "formula": ""
                  }
                }
              ],
              "scaling": {
                "allowed": false,
                "max": ""
              },
              "spellSlot": true
            },
            "description": {
              "chatFlavor": ""
            },
            "duration": {
              "concentration": false,
              "value": "",
              "units": "inst",
              "special": "",
              "override": false
            },
            "effects": [],
            "range": {
              "value": "5",
              "units": "ft",
              "special": "",
              "override": false
            },
            "target": {
              "template": {
                "count": "",
                "contiguous": false,
                "type": "",
                "size": "",
                "width": "",
                "height": "",
                "units": ""
              },
              "affects": {
                "count": "",
                "type": "",
                "choice": false,
                "special": ""
              },
              "prompt": true,
              "override": false
            },
            "uses": {
              "spent": 0,
              "max": "",
              "recovery": []
            },
            "damage": {
              "onSave": "half",
              "parts": [
                {
                  "number": null,
                  "denomination": null,
                  "bonus": "",
                  "types": [
                    "lightning"
                  ],
                  "custom": {
                    "enabled": true,
                    "formula": "3d8[lightning]"
                  },
                  "scaling": {
                    "mode": "whole",
                    "number": null,
                    "formula": ""
                  }
                }
              ],
              "critical": {
                "allow": false
              }
            },
            "save": {
              "ability": [
                "con"
              ],
              "dc": {
                "calculation": "",
                "formula": "12"
              }
            },
            "sort": 0,
            "useConditionText": "",
            "useConditionReason": "",
            "effectConditionText": "",
            "macroData": {
              "name": "",
              "command": ""
            },
            "ignoreTraits": {
              "idi": false,
              "idr": false,
              "idv": false,
              "ida": false
            },
            "midiProperties": {
              "ignoreTraits": [],
              "triggeredActivityId": "none",
              "triggeredActivityConditionText": "",
              "triggeredActivityTargets": "targets",
              "triggeredActivityRollAs": "self",
              "forceDialog": false,
              "confirmTargets": "default",
              "autoTargetType": "any",
              "autoTargetAction": "default",
              "automationOnly": false,
              "otherActivityCompatible": true,
              "identifier": "",
              "displayActivityName": false,
              "rollMode": "default",
              "chooseEffects": false,
              "toggleEffect": false,
              "ignoreFullCover": false
            },
            "isOverTimeFlag": false,
            "overTimeProperties": {
              "saveRemoves": true,
              "preRemoveConditionText": "",
              "postRemoveConditionText": ""
            },
            "otherActivityId": ""
          }
        },
        "identifier": "",
        "advancement": [],
        "enchant": {},
        "prerequisites": {
          "level": null,
          "repeatable": false
        }
      },
      "effects": [],
      "flags": {
        "ddbimporter": {
          "levelBonus": false,
          "dndbeyond": {}
        },
        "monsterMunch": {
          "titleHTML": "<strong>Lightning Jolt (Recharge 5–6).</strong>",
          "fullName": "Lightning Jolt (Recharge 5–6).",
          "actionCopy": false,
          "type": "action",
          "actionInfo": {
            "damage": {
              "parts": [
                [
                  "3d8[lightning]",
                  "lightning"
                ]
              ],
              "versatile": ""
            },
            "baseAbility": null,
            "toHit": 0,
            "proficient": false,
            "extraAttackBonus": 0
          }
        },
        "midi-qol": {
          "removeAttackDamageButtons": "default"
        },
        "midiProperties": {
          "confirmTargets": "default"
        },
        "dnd5e": {}
      },
      "img": "icons/magic/lightning/bolt-forked-teal.webp",
      "folder": null,
      "sort": 0,
      "ownership": {
        "default": 0
      },
      "_stats": {
        "systemId": null,
        "systemVersion": null,
        "coreVersion": "12.331",
        "createdTime": null,
        "modifiedTime": null,
        "lastModifiedBy": null,
        "compendiumSource": null,
        "duplicateSource": null
      },
      "_key": "!actors.items!8ooSMykLkZsMG0Du.cybSoIVrQZ4iOyzk"
    },
    {
      "_id": "CZOouQnl9pUzfsjE",
      "name": "Water Breathing",
      "type": "feat",
      "system": {
        "description": {
          "value": "<div class=\"ddb\">\n<section class=\"secret\">\n<p><em><strong>Water Breathing.</strong></em> The eel can breathe only underwater.</p>\n</section>\nThe [[lookup @name]] uses [[lookup @item.name]].\n</div>",
          "chat": ""
        },
        "source": {
          "book": "Tales from the Yawning Portal",
          "custom": "",
          "license": "",
          "revision": 1,
          "rules": "2024"
        },
        "activation": {
          "cost": null,
          "type": "",
          "condition": ""
        },
        "duration": {
          "value": "",
          "units": ""
        },
        "cover": null,
        "crewed": false,
        "target": {
          "value": null,
          "width": null,
          "units": "",
          "type": "",
          "prompt": true
        },
        "range": {
          "value": null,
          "long": null,
          "units": ""
        },
        "uses": {
          "value": null,
          "max": "",
          "per": null,
          "recovery": [],
          "prompt": true,
          "spent": 0
        },
        "consume": {
          "type": "",
          "target": null,
          "amount": null,
          "scale": false
        },
        "ability": null,
        "actionType": null,
        "attack": {
          "bonus": "",
          "flat": false
        },
        "chatFlavor": "",
        "critical": {
          "threshold": null,
          "damage": ""
        },
        "damage": {
          "parts": [],
          "versatile": ""
        },
        "formula": "",
        "save": {
          "dc": null,
          "ability": "",
          "scaling": "flat"
        },
        "summons": null,
        "type": {
          "value": "monster",
          "subtype": ""
        },
        "properties": [],
        "requirements": "",
        "recharge": {
          "value": null,
          "charged": false
        },
        "activities": {},
        "identifier": "",
        "advancement": [],
        "enchant": {},
        "prerequisites": {
          "level": null,
          "repeatable": false
        }
      },
      "effects": [],
      "flags": {
        "ddbimporter": {
          "levelBonus": false,
          "dndbeyond": {}
        },
        "monsterMunch": {
          "titleHTML": "<em><strong>Water Breathing.</strong></em>",
          "fullName": "Water Breathing.",
          "actionCopy": false,
          "type": "special",
          "actionInfo": {
            "damage": {
              "parts": [],
              "versatile": ""
            },
            "baseAbility": null,
            "toHit": 0,
            "proficient": false,
            "extraAttackBonus": 0
          }
        },
        "midi-qol": {
          "removeAttackDamageButtons": "default"
        },
        "midiProperties": {
          "confirmTargets": "default"
        }
      },
      "img": "icons/magic/air/wind-swirl-purple-blue.webp",
      "folder": null,
      "sort": 0,
      "ownership": {
        "default": 0
      },
      "_stats": {
        "systemId": null,
        "systemVersion": null,
        "coreVersion": "12.331",
        "createdTime": null,
        "modifiedTime": null,
        "lastModifiedBy": null,
        "compendiumSource": null,
        "duplicateSource": null
      },
      "_key": "!actors.items!8ooSMykLkZsMG0Du.CZOouQnl9pUzfsjE"
    }
  ],
  "effects": [],
  "folder": "GgS6jStvmhYXiwLY",
  "sort": 2200000,
  "ownership": {
    "default": 0,
    "6yhz13iFYYklKtgA": 3
  },
  "flags": {
    "dnd5e": {},
    "monsterMunch": {
      "url": "https://www.dndbeyond.com/monsters/22564-giant-lightning-eel",
      "img": "https://www.dndbeyond.com/avatars/4675/664/636747837303835953.jpeg",
      "tokenImg": "https://www.dndbeyond.com/avatars/4675/664/636747837303835953.jpeg",
      "isStockImg": true,
      "spellList": {
        "class": [],
        "pact": [],
        "atwill": [],
        "innate": [],
        "edgeCases": [],
        "material": true,
        "innateMatch": false
      }
    },
    "ddbimporter": {
      "id": 22564,
      "entityTypeId": 779871897,
      "creatureGroupId": null,
      "creatureFlags": [],
      "version": "5.1.27",
      "isLegacy": false,
      "flatAC": false
    }
  },
  "_stats": {
    "systemId": "dnd5e",
    "systemVersion": "4.4.2",
    "coreVersion": "12.343",
    "createdTime": 1721275272744,
    "modifiedTime": 1748178635547,
    "lastModifiedBy": "6yhz13iFYYklKtgA",
    "compendiumSource": null,
    "duplicateSource": null
  },
  "_key": "!actors!8ooSMykLkZsMG0Du"
}
