{
  "name": "Mage Hunter",
  "type": "npc",
  "_id": "Yf70caDuXoT6nK2N",
  "img": "https://www.dndbeyond.com/avatars/thumbnails/22135/808/1000/1000/637743395578827049.jpeg",
  "system": {
    "currency": {
      "pp": 0,
      "gp": 0,
      "ep": 0,
      "sp": 0,
      "cp": 0
    },
    "abilities": {
      "str": {
        "value": 19,
        "proficient": 0,
        "max": null,
        "bonuses": {
          "check": "",
          "save": ""
        }
      },
      "dex": {
        "value": 15,
        "proficient": 0,
        "max": null,
        "bonuses": {
          "check": "",
          "save": ""
        }
      },
      "con": {
        "value": 16,
        "proficient": 0,
        "max": null,
        "bonuses": {
          "check": "",
          "save": ""
        }
      },
      "int": {
        "value": 11,
        "proficient": 1,
        "max": null,
        "bonuses": {
          "check": "",
          "save": ""
        }
      },
      "wis": {
        "value": 17,
        "proficient": 1,
        "max": null,
        "bonuses": {
          "check": "",
          "save": ""
        }
      },
      "cha": {
        "value": 10,
        "proficient": 1,
        "max": null,
        "bonuses": {
          "check": "",
          "save": ""
        }
      }
    },
    "bonuses": {
      "mwak": {
        "attack": "",
        "damage": ""
      },
      "rwak": {
        "attack": "",
        "damage": ""
      },
      "msak": {
        "attack": "",
        "damage": ""
      },
      "rsak": {
        "attack": "",
        "damage": ""
      },
      "abilities": {
        "check": "",
        "save": "",
        "skill": ""
      },
      "spell": {
        "dc": ""
      }
    },
    "skills": {
      "acr": {
        "ability": "dex",
        "roll": {
          "min": null,
          "max": null,
          "mode": 0
        },
        "value": 0,
        "bonuses": {
          "check": "",
          "passive": ""
        }
      },
      "ani": {
        "ability": "wis",
        "roll": {
          "min": null,
          "max": null,
          "mode": 0
        },
        "value": 0,
        "bonuses": {
          "check": "",
          "passive": ""
        }
      },
      "arc": {
        "ability": "int",
        "roll": {
          "min": null,
          "max": null,
          "mode": 0
        },
        "value": 0,
        "bonuses": {
          "check": "",
          "passive": ""
        }
      },
      "ath": {
        "ability": "str",
        "roll": {
          "min": null,
          "max": null,
          "mode": 0
        },
        "value": 0,
        "bonuses": {
          "check": "",
          "passive": ""
        }
      },
      "dec": {
        "ability": "cha",
        "roll": {
          "min": null,
          "max": null,
          "mode": 0
        },
        "value": 0,
        "bonuses": {
          "check": "",
          "passive": ""
        }
      },
      "his": {
        "ability": "int",
        "roll": {
          "min": null,
          "max": null,
          "mode": 0
        },
        "value": 0,
        "bonuses": {
          "check": "",
          "passive": ""
        }
      },
      "ins": {
        "ability": "wis",
        "roll": {
          "min": null,
          "max": null,
          "mode": 0
        },
        "value": 0,
        "bonuses": {
          "check": "",
          "passive": ""
        }
      },
      "itm": {
        "ability": "cha",
        "roll": {
          "min": null,
          "max": null,
          "mode": 0
        },
        "value": 0,
        "bonuses": {
          "check": "",
          "passive": ""
        }
      },
      "inv": {
        "ability": "int",
        "roll": {
          "min": null,
          "max": null,
          "mode": 0
        },
        "value": 0,
        "bonuses": {
          "check": "",
          "passive": ""
        }
      },
      "med": {
        "ability": "wis",
        "roll": {
          "min": null,
          "max": null,
          "mode": 0
        },
        "value": 0,
        "bonuses": {
          "check": "",
          "passive": ""
        }
      },
      "nat": {
        "ability": "int",
        "roll": {
          "min": null,
          "max": null,
          "mode": 0
        },
        "value": 0,
        "bonuses": {
          "check": "",
          "passive": ""
        }
      },
      "prc": {
        "ability": "wis",
        "roll": {
          "min": null,
          "max": null,
          "mode": 0
        },
        "value": 2,
        "bonuses": {
          "check": "",
          "passive": ""
        }
      },
      "prf": {
        "ability": "cha",
        "roll": {
          "min": null,
          "max": null,
          "mode": 0
        },
        "value": 0,
        "bonuses": {
          "check": "",
          "passive": ""
        }
      },
      "per": {
        "ability": "cha",
        "roll": {
          "min": null,
          "max": null,
          "mode": 0
        },
        "value": 0,
        "bonuses": {
          "check": "",
          "passive": ""
        }
      },
      "rel": {
        "ability": "int",
        "roll": {
          "min": null,
          "max": null,
          "mode": 0
        },
        "value": 0,
        "bonuses": {
          "check": "",
          "passive": ""
        }
      },
      "slt": {
        "ability": "dex",
        "roll": {
          "min": null,
          "max": null,
          "mode": 0
        },
        "value": 0,
        "bonuses": {
          "check": "",
          "passive": ""
        }
      },
      "ste": {
        "ability": "dex",
        "roll": {
          "min": null,
          "max": null,
          "mode": 0
        },
        "value": 1,
        "bonuses": {
          "check": "",
          "passive": ""
        }
      },
      "sur": {
        "ability": "wis",
        "roll": {
          "min": null,
          "max": null,
          "mode": 0
        },
        "value": 0,
        "bonuses": {
          "check": "",
          "passive": ""
        }
      }
    },
    "tools": {},
    "spells": {
      "spell1": {
        "value": 0,
        "override": null
      },
      "spell2": {
        "value": 0,
        "override": null
      },
      "spell3": {
        "value": 0,
        "override": null
      },
      "spell4": {
        "value": 0,
        "override": null
      },
      "spell5": {
        "value": 0,
        "override": null
      },
      "spell6": {
        "value": 0,
        "override": null
      },
      "spell7": {
        "value": 0,
        "override": null
      },
      "spell8": {
        "value": 0,
        "override": null
      },
      "spell9": {
        "value": 0,
        "override": null
      },
      "pact": {
        "value": 0,
        "override": null
      }
    },
    "attributes": {
      "init": {
        "ability": "",
        "roll": {
          "min": null,
          "max": null,
          "mode": 0
        },
        "bonus": ""
      },
      "movement": {
        "burrow": null,
        "climb": 40,
        "fly": 10,
        "swim": null,
        "walk": 40,
        "units": "ft",
        "hover": false
      },
      "attunement": {
        "max": 3
      },
      "senses": {
        "darkvision": 0,
        "blindsight": 120,
        "tremorsense": 0,
        "truesight": 0,
        "units": "ft",
        "special": ""
      },
      "spellcasting": "int",
      "exhaustion": 0,
      "concentration": {
        "ability": "",
        "roll": {
          "min": null,
          "max": null,
          "mode": 0
        },
        "bonuses": {
          "save": ""
        },
        "limit": 1
      },
      "ac": {
        "flat": 15,
        "calc": "natural",
        "formula": ""
      },
      "hp": {
        "value": 85,
        "max": 85,
        "temp": 0,
        "tempmax": 0,
        "formula": "10d10 + 30"
      },
      "death": {
        "ability": "",
        "roll": {
          "min": null,
          "max": null,
          "mode": 0
        },
        "success": 0,
        "failure": 0
      }
    },
    "details": {
      "biography": {
        "value": "<p>Mage hunters are hideous spider-legged creatures employed by the Oriq to pursue magic-wielders. These creatures can naturally sense magic via the glowing purple spines on their backs.</p>\n<p>A mage hunter is usually in its sentry form, a diamond-shaped drone with a heightened ability to sense and locate mages. Once it finds a quarry, the mage hunter takes on its arachnoid hunter form and pursues its targets with vicious skill.</p>",
        "public": ""
      },
      "alignment": "Typically Lawful Evil",
      "race": null,
      "type": {
        "value": "monstrosity",
        "subtype": ""
      },
      "environment": "",
      "cr": 5,
      "spellLevel": 0,
      "source": {
        "book": "Strixhaven: A Curriculum of Chaos",
        "page": "199",
        "custom": "",
        "license": ""
      }
    },
    "resources": {
      "legact": {
        "value": 0,
        "max": 0
      },
      "legres": {
        "value": 0,
        "max": 0
      },
      "lair": {
        "value": false,
        "initiative": null
      }
    },
    "traits": {
      "size": "lg",
      "di": {
        "value": [],
        "bypasses": [],
        "custom": ""
      },
      "dr": {
        "value": [],
        "bypasses": [],
        "custom": ""
      },
      "dv": {
        "value": [],
        "bypasses": [],
        "custom": ""
      },
      "dm": {
        "amount": {},
        "bypasses": []
      },
      "ci": {
        "value": [
          "blinded",
          "charmed",
          "deafened",
          "frightened",
          "prone"
        ],
        "custom": ""
      },
      "languages": {
        "value": [],
        "custom": "understands Common but can’t speak"
      }
    }
  },
  "prototypeToken": {
    "name": "Mage Hunter",
    "displayName": 20,
    "actorLink": false,
    "appendNumber": false,
    "prependAdjective": false,
    "texture": {
      "src": "ddb-images/other/npc-token-Mage-Hunter.jpeg",
      "scaleX": 1,
      "scaleY": 1,
      "offsetX": 0,
      "offsetY": 0,
      "rotation": 0
    },
    "width": 2,
    "height": 2,
    "lockRotation": false,
    "rotation": 0,
    "alpha": 1,
    "disposition": -1,
    "displayBars": 20,
    "bar1": {
      "attribute": "attributes.hp"
    },
    "bar2": {
      "attribute": null
    },
    "light": {
      "alpha": 0.5,
      "angle": 360,
      "bright": 0,
      "coloration": 1,
      "dim": 0,
      "attenuation": 0.5,
      "luminosity": 0.5,
      "saturation": 0,
      "contrast": 0,
      "shadows": 0,
      "animation": {
        "type": null,
        "speed": 5,
        "intensity": 5,
        "reverse": false
      },
      "darkness": {
        "min": 0,
        "max": 1
      }
    },
    "sight": {
      "enabled": false,
      "range": 120,
      "angle": 360,
      "visionMode": "basic",
      "color": null,
      "attenuation": 0,
      "brightness": 0,
      "saturation": 0,
      "contrast": 0
    },
    "detectionModes": [
      {
        "id": "senseAll",
        "range": 120,
        "enabled": true
      }
    ],
    "flags": {
      "monks-tokenbar": {
        "include": "default"
      },
      "tagger": {
        "tags": [
          "dndbeyond",
          "ddb-importer",
          "monstrosity"
        ]
      }
    },
    "randomImg": false
  },
  "items": [
    {
      "_id": "fzikekrpnhhLOdgv",
      "name": "Multiattack (Hunter Form Only)",
      "type": "feat",
      "system": {
        "description": {
          "value": "<div class=\"ddb\">\n<section class=\"secret\">\n<p> The hunter makes two Claw attacks.</p>\n</section>\nThe [[lookup @name]] uses [[lookup @item.name]].\n</div>",
          "chat": ""
        },
        "source": {
          "book": "Strixhaven: A Curriculum of Chaos",
          "page": "199",
          "custom": "",
          "license": ""
        },
        "activation": {
          "type": "action",
          "cost": 1,
          "condition": ""
        },
        "duration": {
          "value": "",
          "units": "inst"
        },
        "cover": null,
        "crewed": false,
        "target": {
          "value": null,
          "width": null,
          "units": "",
          "type": "",
          "prompt": true
        },
        "range": {
          "value": null,
          "long": null,
          "units": ""
        },
        "uses": {
          "value": null,
          "max": "",
          "per": null,
          "recovery": "",
          "prompt": true
        },
        "consume": {
          "type": "",
          "target": null,
          "amount": null,
          "scale": false
        },
        "ability": null,
        "actionType": null,
        "attack": {
          "bonus": "",
          "flat": false
        },
        "chatFlavor": "",
        "critical": {
          "threshold": null,
          "damage": ""
        },
        "damage": {
          "parts": [],
          "versatile": ""
        },
        "formula": "",
        "save": {
          "dc": null,
          "ability": "",
          "scaling": "flat"
        },
        "summons": null,
        "type": {
          "value": "monster",
          "subtype": ""
        },
        "properties": [],
        "requirements": "",
        "recharge": {
          "value": null,
          "charged": false
        }
      },
      "effects": [],
      "flags": {
        "ddbimporter": {
          "levelBonus": false,
          "dndbeyond": {}
        },
        "monsterMunch": {
          "titleHTML": "<strong>Multiattack (Hunter Form Only).</strong>",
          "fullName": "Multiattack (Hunter Form Only).",
          "actionCopy": false,
          "type": "action",
          "actionInfo": {
            "damage": {
              "parts": [],
              "versatile": ""
            },
            "baseAbility": null,
            "toHit": 0,
            "proficient": false,
            "extraAttackBonus": 0
          }
        },
        "midi-qol": {
          "removeAttackDamageButtons": "default"
        },
        "midiProperties": {
          "confirmTargets": "default"
        }
      },
      "img": "icons/skills/melee/strike-weapons-orange.webp",
      "folder": null,
      "sort": 0,
      "ownership": {
        "default": 0
      },
      "_stats": {
        "systemId": null,
        "systemVersion": null,
        "coreVersion": null,
        "createdTime": null,
        "modifiedTime": null,
        "lastModifiedBy": null
      },
      "_key": "!actors.items!Yf70caDuXoT6nK2N.fzikekrpnhhLOdgv"
    },
    {
      "_id": "5tamciounlLlLxqq",
      "name": "Claw (Hunter Form Only)",
      "type": "weapon",
      "system": {
        "description": {
          "value": "<div class=\"ddb\">\n<section class=\"secret\">\n<p><em><strong></strong> Melee Weapon Attack:</em> +7 to hit, reach 5 ft., one target. <em>Hit:</em> [[/damage 2d10 + @mod type=slashing average=true]] damage.</p>\n</section>\nThe [[lookup @name]] attacks with its [[lookup @item.name]].\n</div>",
          "chat": ""
        },
        "source": {
          "book": "Strixhaven: A Curriculum of Chaos",
          "page": "199",
          "custom": "",
          "license": ""
        },
        "identified": true,
        "unidentified": {
          "description": ""
        },
        "container": null,
        "quantity": 1,
        "weight": 0,
        "price": {
          "value": 0,
          "denomination": "gp"
        },
        "rarity": "",
        "attunement": 0,
        "equipped": true,
        "activation": {
          "type": "action",
          "cost": 1,
          "condition": ""
        },
        "duration": {
          "value": "",
          "units": "inst"
        },
        "cover": null,
        "crewed": false,
        "target": {
          "value": null,
          "width": null,
          "units": "",
          "type": "",
          "prompt": true
        },
        "range": {
          "value": 5,
          "long": null,
          "units": "ft"
        },
        "uses": {
          "value": null,
          "max": "",
          "per": null,
          "recovery": "",
          "prompt": true
        },
        "consume": {
          "type": "",
          "target": null,
          "amount": null,
          "scale": false
        },
        "ability": "str",
        "actionType": "mwak",
        "attack": {
          "bonus": "",
          "flat": false
        },
        "chatFlavor": "",
        "critical": {
          "threshold": null,
          "damage": ""
        },
        "damage": {
          "parts": [
            [
              "2d10[slashing] + @mod",
              "slashing"
            ]
          ],
          "versatile": ""
        },
        "formula": "",
        "save": {
          "dc": null,
          "ability": "",
          "scaling": "flat"
        },
        "summons": null,
        "armor": {
          "value": null
        },
        "hp": {
          "value": null,
          "max": null,
          "dt": null,
          "conditions": ""
        },
        "type": {
          "value": "natural",
          "baseItem": ""
        },
        "magicalBonus": null,
        "properties": [],
        "proficient": 1
      },
      "effects": [],
      "flags": {
        "ddbimporter": {
          "levelBonus": false,
          "dndbeyond": {}
        },
        "monsterMunch": {
          "titleHTML": "<strong>Claw (Hunter Form Only).</strong>",
          "fullName": "Claw (Hunter Form Only).",
          "actionCopy": false,
          "type": "action",
          "actionInfo": {
            "damage": {
              "parts": [
                [
                  "2d10[slashing] + @mod",
                  "slashing"
                ]
              ],
              "versatile": ""
            },
            "baseAbility": "str",
            "toHit": 7,
            "proficient": true,
            "extraAttackBonus": 0
          }
        },
        "midi-qol": {
          "removeAttackDamageButtons": "default"
        },
        "midiProperties": {
          "confirmTargets": "default"
        }
      },
      "img": "icons/commodities/claws/talon-red.webp",
      "folder": null,
      "sort": 0,
      "ownership": {
        "default": 0
      },
      "_stats": {
        "systemId": null,
        "systemVersion": null,
        "coreVersion": null,
        "createdTime": null,
        "modifiedTime": null,
        "lastModifiedBy": null
      },
      "_key": "!actors.items!Yf70caDuXoT6nK2N.5tamciounlLlLxqq"
    },
    {
      "_id": "s0BDzK6ke4BhtFyn",
      "name": "Tail",
      "type": "weapon",
      "system": {
        "description": {
          "value": "<div class=\"ddb\">\n<section class=\"secret\">\n<p><em><strong></strong> Melee Weapon Attack:</em> +7 to hit, reach 10 ft., one target. <em>Hit:</em> [[/damage 4d8 + @mod type=piercing average=true]] damage, and the target is &amp;Reference[grappled]{grappled} (escape DC 15). Until this grapple ends, the target is &amp;Reference[restrained]{restrained}, and the hunter can’t make a Tail attack against another target.</p>\n</section>\nThe [[lookup @name]] attacks with its [[lookup @item.name]].\n</div>",
          "chat": ""
        },
        "source": {
          "book": "Strixhaven: A Curriculum of Chaos",
          "page": "199",
          "custom": "",
          "license": ""
        },
        "identified": true,
        "unidentified": {
          "description": ""
        },
        "container": null,
        "quantity": 1,
        "weight": 0,
        "price": {
          "value": 0,
          "denomination": "gp"
        },
        "rarity": "",
        "attunement": 0,
        "equipped": true,
        "activation": {
          "type": "action",
          "cost": 1,
          "condition": ""
        },
        "duration": {
          "value": "",
          "units": "inst"
        },
        "cover": null,
        "crewed": false,
        "target": {
          "value": null,
          "width": null,
          "units": "",
          "type": "",
          "prompt": true
        },
        "range": {
          "value": 10,
          "long": null,
          "units": "ft"
        },
        "uses": {
          "value": null,
          "max": "",
          "per": null,
          "recovery": "",
          "prompt": true
        },
        "consume": {
          "type": "",
          "target": null,
          "amount": null,
          "scale": false
        },
        "ability": "str",
        "actionType": "mwak",
        "attack": {
          "bonus": "",
          "flat": false
        },
        "chatFlavor": "",
        "critical": {
          "threshold": null,
          "damage": ""
        },
        "damage": {
          "parts": [
            [
              "4d8[piercing] + @mod",
              "piercing"
            ]
          ],
          "versatile": ""
        },
        "formula": "",
        "save": {
          "dc": null,
          "ability": "",
          "scaling": "flat"
        },
        "summons": null,
        "armor": {
          "value": null
        },
        "hp": {
          "value": null,
          "max": null,
          "dt": null,
          "conditions": ""
        },
        "type": {
          "value": "natural",
          "baseItem": ""
        },
        "magicalBonus": null,
        "properties": [],
        "proficient": 1
      },
      "effects": [],
      "flags": {
        "ddbimporter": {
          "levelBonus": false,
          "dndbeyond": {}
        },
        "monsterMunch": {
          "titleHTML": "<strong>Tail.</strong>",
          "fullName": "Tail.",
          "actionCopy": false,
          "type": "action",
          "actionInfo": {
            "damage": {
              "parts": [
                [
                  "4d8[piercing] + @mod",
                  "piercing"
                ]
              ],
              "versatile": ""
            },
            "baseAbility": "str",
            "toHit": 7,
            "proficient": true,
            "extraAttackBonus": 0
          }
        },
        "midi-qol": {
          "removeAttackDamageButtons": "default"
        },
        "midiProperties": {
          "confirmTargets": "default"
        }
      },
      "img": "icons/commodities/biological/tail-scaled-green.webp",
      "folder": null,
      "sort": 0,
      "ownership": {
        "default": 0
      },
      "_stats": {
        "systemId": null,
        "systemVersion": null,
        "coreVersion": null,
        "createdTime": null,
        "modifiedTime": null,
        "lastModifiedBy": null
      },
      "_key": "!actors.items!Yf70caDuXoT6nK2N.s0BDzK6ke4BhtFyn"
    },
    {
      "_id": "zRoTrONKScQeiE7u",
      "name": "Mage Tracker (Sentry Form Only)",
      "type": "feat",
      "system": {
        "description": {
          "value": "<div class=\"ddb\">\n<section class=\"secret\">\n<p> The hunter emits a pulse of energy that helps it better locate its magical quarry. Each creature within 120 feet of the hunter that has the ability to cast spells must succeed on a [[/save wis 14 format=long]] or be mystically marked by the hunter for 1 hour.</p><p>While marked, a creature can’t become hidden from the hunter and gains no benefit from the &amp;Reference[invisible]{invisible} condition against the hunter. Additionally, while a marked creature is on the same plane of existence as the hunter, the hunter always knows the distance and direction to the creature.</p>\n</section>\nThe [[lookup @name]] uses [[lookup @item.name]] and a save is required.\n</div>",
          "chat": ""
        },
        "source": {
          "book": "Strixhaven: A Curriculum of Chaos",
          "page": "199",
          "custom": "",
          "license": ""
        },
        "activation": {
          "type": "action",
          "cost": 1,
          "condition": ""
        },
        "duration": {
          "value": "",
          "units": "inst"
        },
        "cover": null,
        "crewed": false,
        "target": {
          "value": null,
          "width": null,
          "units": "",
          "type": "",
          "prompt": true
        },
        "range": {
          "value": 120,
          "long": null,
          "units": "ft"
        },
        "uses": {
          "value": null,
          "max": "",
          "per": null,
          "recovery": "",
          "prompt": true
        },
        "consume": {
          "type": "",
          "target": null,
          "amount": null,
          "scale": false
        },
        "ability": null,
        "actionType": "save",
        "attack": {
          "bonus": "",
          "flat": false
        },
        "chatFlavor": "",
        "critical": {
          "threshold": null,
          "damage": ""
        },
        "damage": {
          "parts": [],
          "versatile": ""
        },
        "formula": "",
        "save": {
          "dc": 14,
          "ability": "wis",
          "scaling": "flat"
        },
        "summons": null,
        "type": {
          "value": "monster",
          "subtype": ""
        },
        "properties": [],
        "requirements": "",
        "recharge": {
          "value": null,
          "charged": false
        }
      },
      "effects": [],
      "flags": {
        "ddbimporter": {
          "levelBonus": false,
          "dndbeyond": {}
        },
        "monsterMunch": {
          "titleHTML": "<strong>Mage Tracker (Sentry Form Only).</strong>",
          "fullName": "Mage Tracker (Sentry Form Only).",
          "actionCopy": false,
          "type": "action",
          "actionInfo": {
            "damage": {
              "parts": [],
              "versatile": ""
            },
            "baseAbility": null,
            "toHit": 0,
            "proficient": false,
            "extraAttackBonus": 0
          }
        },
        "midi-qol": {
          "removeAttackDamageButtons": "default"
        },
        "midiProperties": {
          "confirmTargets": "default",
          "fulldam": true
        }
      },
      "img": "systems/dnd5e/icons/svg/items/feature.svg",
      "folder": null,
      "sort": 0,
      "ownership": {
        "default": 0
      },
      "_stats": {
        "systemId": null,
        "systemVersion": null,
        "coreVersion": null,
        "createdTime": null,
        "modifiedTime": null,
        "lastModifiedBy": null
      },
      "_key": "!actors.items!Yf70caDuXoT6nK2N.zRoTrONKScQeiE7u"
    },
    {
      "_id": "4PSVP1N6YrMDSIoW",
      "name": "Magic Sense",
      "type": "feat",
      "system": {
        "description": {
          "value": "<div class=\"ddb\">\n<section class=\"secret\">\n<p><em><strong>Magic Sense.</strong></em> The hunter knows the location of every spellcaster, active spell, and magic item within 120 feet of itself.</p>\n</section>\nThe [[lookup @name]] uses [[lookup @item.name]].\n</div>",
          "chat": ""
        },
        "source": {
          "book": "Strixhaven: A Curriculum of Chaos",
          "page": "199",
          "custom": "",
          "license": ""
        },
        "activation": {
          "cost": null,
          "type": "",
          "condition": ""
        },
        "duration": {
          "value": "",
          "units": ""
        },
        "cover": null,
        "crewed": false,
        "target": {
          "value": null,
          "width": null,
          "units": "",
          "type": "",
          "prompt": true
        },
        "range": {
          "value": null,
          "long": null,
          "units": ""
        },
        "uses": {
          "value": null,
          "max": "",
          "per": null,
          "recovery": "",
          "prompt": true
        },
        "consume": {
          "type": "",
          "target": null,
          "amount": null,
          "scale": false
        },
        "ability": null,
        "actionType": null,
        "attack": {
          "bonus": "",
          "flat": false
        },
        "chatFlavor": "",
        "critical": {
          "threshold": null,
          "damage": ""
        },
        "damage": {
          "parts": [],
          "versatile": ""
        },
        "formula": "",
        "save": {
          "dc": null,
          "ability": "",
          "scaling": "flat"
        },
        "summons": null,
        "type": {
          "value": "monster",
          "subtype": ""
        },
        "properties": [],
        "requirements": "",
        "recharge": {
          "value": null,
          "charged": false
        }
      },
      "effects": [],
      "flags": {
        "ddbimporter": {
          "levelBonus": false,
          "dndbeyond": {}
        },
        "monsterMunch": {
          "titleHTML": "<em><strong>Magic Sense.</strong></em>",
          "fullName": "Magic Sense.",
          "actionCopy": false,
          "type": "special",
          "actionInfo": {
            "damage": {
              "parts": [],
              "versatile": ""
            },
            "baseAbility": null,
            "toHit": 0,
            "proficient": false,
            "extraAttackBonus": 0
          }
        },
        "midi-qol": {
          "removeAttackDamageButtons": "default"
        },
        "midiProperties": {
          "confirmTargets": "default"
        }
      },
      "img": "systems/dnd5e/icons/svg/items/feature.svg",
      "folder": null,
      "sort": 0,
      "ownership": {
        "default": 0
      },
      "_stats": {
        "systemId": null,
        "systemVersion": null,
        "coreVersion": null,
        "createdTime": null,
        "modifiedTime": null,
        "lastModifiedBy": null
      },
      "_key": "!actors.items!Yf70caDuXoT6nK2N.4PSVP1N6YrMDSIoW"
    },
    {
      "_id": "dl7EebGrug8QaDR1",
      "name": "Spider Climb (Hunter Form Only)",
      "type": "feat",
      "system": {
        "description": {
          "value": "<div class=\"ddb\">\n<section class=\"secret\">\n<p><em><strong>Spider Climb (Hunter Form Only).</strong></em> The hunter can climb difficult surfaces, including upside down on ceilings, without needing to make an ability check.</p>\n</section>\nThe [[lookup @name]] uses [[lookup @item.name]].\n</div>",
          "chat": ""
        },
        "source": {
          "book": "Strixhaven: A Curriculum of Chaos",
          "page": "199",
          "custom": "",
          "license": ""
        },
        "activation": {
          "cost": null,
          "type": "",
          "condition": ""
        },
        "duration": {
          "value": "",
          "units": ""
        },
        "cover": null,
        "crewed": false,
        "target": {
          "value": null,
          "width": null,
          "units": "",
          "type": "",
          "prompt": true
        },
        "range": {
          "value": null,
          "long": null,
          "units": ""
        },
        "uses": {
          "value": null,
          "max": "",
          "per": null,
          "recovery": "",
          "prompt": true
        },
        "consume": {
          "type": "",
          "target": null,
          "amount": null,
          "scale": false
        },
        "ability": null,
        "actionType": null,
        "attack": {
          "bonus": "",
          "flat": false
        },
        "chatFlavor": "",
        "critical": {
          "threshold": null,
          "damage": ""
        },
        "damage": {
          "parts": [],
          "versatile": ""
        },
        "formula": "",
        "save": {
          "dc": null,
          "ability": "",
          "scaling": "flat"
        },
        "summons": null,
        "type": {
          "value": "monster",
          "subtype": ""
        },
        "properties": [],
        "requirements": "",
        "recharge": {
          "value": null,
          "charged": false
        }
      },
      "effects": [],
      "flags": {
        "ddbimporter": {
          "levelBonus": false,
          "dndbeyond": {}
        },
        "monsterMunch": {
          "titleHTML": "<em><strong>Spider Climb (Hunter Form Only).</strong></em>",
          "fullName": "Spider Climb (Hunter Form Only).",
          "actionCopy": false,
          "type": "special",
          "actionInfo": {
            "damage": {
              "parts": [],
              "versatile": ""
            },
            "baseAbility": null,
            "toHit": 0,
            "proficient": false,
            "extraAttackBonus": 0
          }
        },
        "midi-qol": {
          "removeAttackDamageButtons": "default"
        },
        "midiProperties": {
          "confirmTargets": "default"
        }
      },
      "img": "icons/creatures/invertebrates/spider-beetle-runed-green.webp",
      "folder": null,
      "sort": 0,
      "ownership": {
        "default": 0
      },
      "_stats": {
        "systemId": null,
        "systemVersion": null,
        "coreVersion": null,
        "createdTime": null,
        "modifiedTime": null,
        "lastModifiedBy": null
      },
      "_key": "!actors.items!Yf70caDuXoT6nK2N.dl7EebGrug8QaDR1"
    },
    {
      "_id": "zJTdRRcT2FH4IFlo",
      "name": "Consume and Destroy",
      "type": "feat",
      "system": {
        "description": {
          "value": "<div class=\"ddb\">\n<section class=\"secret\">\n<p> When the hunter takes damage from a spell, it takes only half the triggering damage (rounded down). If the creature that cast the spell is within 60 feet of the hunter, that creature must succeed on a [[/save dex 14 format=long]] or take the other half of the damage.</p>\n</section>\nThe [[lookup @name]] uses [[lookup @item.name]] and a save is required.\n</div>",
          "chat": ""
        },
        "source": {
          "book": "Strixhaven: A Curriculum of Chaos",
          "page": "199",
          "custom": "",
          "license": ""
        },
        "activation": {
          "type": "reaction",
          "cost": 1,
          "condition": ""
        },
        "duration": {
          "value": "",
          "units": "inst"
        },
        "cover": null,
        "crewed": false,
        "target": {
          "value": null,
          "width": null,
          "units": "",
          "type": "",
          "prompt": true
        },
        "range": {
          "value": 60,
          "long": null,
          "units": "ft"
        },
        "uses": {
          "value": null,
          "max": "",
          "per": null,
          "recovery": "",
          "prompt": true
        },
        "consume": {
          "type": "",
          "target": null,
          "amount": null,
          "scale": false
        },
        "ability": null,
        "actionType": "save",
        "attack": {
          "bonus": "",
          "flat": false
        },
        "chatFlavor": "",
        "critical": {
          "threshold": null,
          "damage": ""
        },
        "damage": {
          "parts": [],
          "versatile": ""
        },
        "formula": "",
        "save": {
          "dc": 14,
          "ability": "dex",
          "scaling": "flat"
        },
        "summons": null,
        "type": {
          "value": "monster",
          "subtype": ""
        },
        "properties": [],
        "requirements": "",
        "recharge": {
          "value": null,
          "charged": false
        }
      },
      "effects": [],
      "flags": {
        "ddbimporter": {
          "levelBonus": false,
          "dndbeyond": {}
        },
        "monsterMunch": {
          "titleHTML": "<strong>Consume and Destroy.</strong>",
          "fullName": "Consume and Destroy.",
          "actionCopy": false,
          "type": "reaction",
          "actionInfo": {
            "damage": {
              "parts": [],
              "versatile": ""
            },
            "baseAbility": null,
            "toHit": 0,
            "proficient": false,
            "extraAttackBonus": 0
          }
        },
        "midi-qol": {
          "removeAttackDamageButtons": "default"
        },
        "midiProperties": {
          "confirmTargets": "default"
        }
      },
      "img": "systems/dnd5e/icons/svg/items/feature.svg",
      "folder": null,
      "sort": 0,
      "ownership": {
        "default": 0
      },
      "_stats": {
        "systemId": null,
        "systemVersion": null,
        "coreVersion": null,
        "createdTime": null,
        "modifiedTime": null,
        "lastModifiedBy": null
      },
      "_key": "!actors.items!Yf70caDuXoT6nK2N.zJTdRRcT2FH4IFlo"
    },
    {
      "_id": "n8s8TW0FvQMwwKF6",
      "name": "Shift Form",
      "type": "feat",
      "system": {
        "description": {
          "value": "<div class=\"ddb\">\n<section class=\"secret\">\n<p> The hunter folds into its drone-like sentry form or unfolds into its hunter form. Its game statistics are the same in each form.</p>\n</section>\nThe [[lookup @name]] uses [[lookup @item.name]].\n</div>",
          "chat": ""
        },
        "source": {
          "book": "Strixhaven: A Curriculum of Chaos",
          "page": "199",
          "custom": "",
          "license": ""
        },
        "activation": {
          "type": "bonus",
          "cost": 1,
          "condition": ""
        },
        "duration": {
          "value": "",
          "units": "inst"
        },
        "cover": null,
        "crewed": false,
        "target": {
          "value": null,
          "width": null,
          "units": "",
          "type": "",
          "prompt": true
        },
        "range": {
          "value": null,
          "long": null,
          "units": ""
        },
        "uses": {
          "value": null,
          "max": "",
          "per": null,
          "recovery": "",
          "prompt": true
        },
        "consume": {
          "type": "",
          "target": null,
          "amount": null,
          "scale": false
        },
        "ability": null,
        "actionType": null,
        "attack": {
          "bonus": "",
          "flat": false
        },
        "chatFlavor": "",
        "critical": {
          "threshold": null,
          "damage": ""
        },
        "damage": {
          "parts": [],
          "versatile": ""
        },
        "formula": "",
        "save": {
          "dc": null,
          "ability": "",
          "scaling": "flat"
        },
        "summons": null,
        "type": {
          "value": "monster",
          "subtype": ""
        },
        "properties": [],
        "requirements": "",
        "recharge": {
          "value": null,
          "charged": false
        }
      },
      "effects": [],
      "flags": {
        "ddbimporter": {
          "levelBonus": false,
          "dndbeyond": {}
        },
        "monsterMunch": {
          "titleHTML": "<strong>Shift Form.</strong>",
          "fullName": "Shift Form.",
          "actionCopy": false,
          "type": "bonus",
          "actionInfo": {
            "damage": {
              "parts": [],
              "versatile": ""
            },
            "baseAbility": null,
            "toHit": 0,
            "proficient": false,
            "extraAttackBonus": 0
          }
        },
        "midi-qol": {
          "removeAttackDamageButtons": "default"
        },
        "midiProperties": {
          "confirmTargets": "default"
        }
      },
      "img": "systems/dnd5e/icons/svg/items/feature.svg",
      "folder": null,
      "sort": 0,
      "ownership": {
        "default": 0
      },
      "_stats": {
        "systemId": null,
        "systemVersion": null,
        "coreVersion": null,
        "createdTime": null,
        "modifiedTime": null,
        "lastModifiedBy": null
      },
      "_key": "!actors.items!Yf70caDuXoT6nK2N.n8s8TW0FvQMwwKF6"
    }
  ],
  "effects": [],
  "folder": "OdQClMm2HO5KTQjz",
  "sort": 9700000,
  "ownership": {
    "default": 0,
    "6yhz13iFYYklKtgA": 3
  },
  "flags": {
    "dnd5e": {},
    "monsterMunch": {
      "url": "https://www.dndbeyond.com/monsters/2160312-mage-hunter",
      "img": "https://www.dndbeyond.com/avatars/thumbnails/22135/808/1000/1000/637743395578827049.jpeg",
      "tokenImg": "https://www.dndbeyond.com/avatars/22135/807/637743395577856955.jpeg",
      "isStockImg": false,
      "spellList": {
        "class": [],
        "pact": [],
        "atwill": [],
        "innate": [],
        "edgeCases": [],
        "material": true,
        "innateMatch": false
      }
    },
    "ddbimporter": {
      "id": 2160312,
      "entityTypeId": 779871897,
      "creatureGroupId": null,
      "creatureFlags": [],
      "version": "5.1.27",
      "isLegacy": false,
      "flatAC": false
    }
  },
  "_stats": {
    "systemId": "dnd5e",
    "systemVersion": "3.1.2",
    "coreVersion": "11.315",
    "createdTime": 1721275295456,
    "modifiedTime": 1727200515655,
    "lastModifiedBy": "6yhz13iFYYklKtgA"
  },
  "_key": "!actors!Yf70caDuXoT6nK2N"
}
