{
  "name": "Mindwitness",
  "type": "npc",
  "_id": "OLlt8s6BCI3tnMsi",
  "img": "https://www.dndbeyond.com/avatars/25746/533/637880557825677939.png",
  "system": {
    "currency": {
      "pp": 0,
      "gp": 0,
      "ep": 0,
      "sp": 0,
      "cp": 0
    },
    "abilities": {
      "str": {
        "value": 10,
        "proficient": 0,
        "max": null,
        "bonuses": {
          "check": "",
          "save": ""
        }
      },
      "dex": {
        "value": 14,
        "proficient": 0,
        "max": null,
        "bonuses": {
          "check": "",
          "save": ""
        }
      },
      "con": {
        "value": 14,
        "proficient": 0,
        "max": null,
        "bonuses": {
          "check": "",
          "save": ""
        }
      },
      "int": {
        "value": 15,
        "proficient": 1,
        "max": null,
        "bonuses": {
          "check": "",
          "save": ""
        }
      },
      "wis": {
        "value": 15,
        "proficient": 1,
        "max": null,
        "bonuses": {
          "check": "",
          "save": ""
        }
      },
      "cha": {
        "value": 10,
        "proficient": 0,
        "max": null,
        "bonuses": {
          "check": "",
          "save": ""
        }
      }
    },
    "bonuses": {
      "mwak": {
        "attack": "",
        "damage": ""
      },
      "rwak": {
        "attack": "",
        "damage": ""
      },
      "msak": {
        "attack": "",
        "damage": ""
      },
      "rsak": {
        "attack": "",
        "damage": ""
      },
      "abilities": {
        "check": "",
        "save": "",
        "skill": ""
      },
      "spell": {
        "dc": ""
      }
    },
    "skills": {
      "acr": {
        "ability": "dex",
        "roll": {
          "min": null,
          "max": null,
          "mode": 0
        },
        "value": 0,
        "bonuses": {
          "check": "",
          "passive": ""
        }
      },
      "ani": {
        "ability": "wis",
        "roll": {
          "min": null,
          "max": null,
          "mode": 0
        },
        "value": 0,
        "bonuses": {
          "check": "",
          "passive": ""
        }
      },
      "arc": {
        "ability": "int",
        "roll": {
          "min": null,
          "max": null,
          "mode": 0
        },
        "value": 0,
        "bonuses": {
          "check": "",
          "passive": ""
        }
      },
      "ath": {
        "ability": "str",
        "roll": {
          "min": null,
          "max": null,
          "mode": 0
        },
        "value": 0,
        "bonuses": {
          "check": "",
          "passive": ""
        }
      },
      "dec": {
        "ability": "cha",
        "roll": {
          "min": null,
          "max": null,
          "mode": 0
        },
        "value": 0,
        "bonuses": {
          "check": "",
          "passive": ""
        }
      },
      "his": {
        "ability": "int",
        "roll": {
          "min": null,
          "max": null,
          "mode": 0
        },
        "value": 0,
        "bonuses": {
          "check": "",
          "passive": ""
        }
      },
      "ins": {
        "ability": "wis",
        "roll": {
          "min": null,
          "max": null,
          "mode": 0
        },
        "value": 0,
        "bonuses": {
          "check": "",
          "passive": ""
        }
      },
      "itm": {
        "ability": "cha",
        "roll": {
          "min": null,
          "max": null,
          "mode": 0
        },
        "value": 0,
        "bonuses": {
          "check": "",
          "passive": ""
        }
      },
      "inv": {
        "ability": "int",
        "roll": {
          "min": null,
          "max": null,
          "mode": 0
        },
        "value": 0,
        "bonuses": {
          "check": "",
          "passive": ""
        }
      },
      "med": {
        "ability": "wis",
        "roll": {
          "min": null,
          "max": null,
          "mode": 0
        },
        "value": 0,
        "bonuses": {
          "check": "",
          "passive": ""
        }
      },
      "nat": {
        "ability": "int",
        "roll": {
          "min": null,
          "max": null,
          "mode": 0
        },
        "value": 0,
        "bonuses": {
          "check": "",
          "passive": ""
        }
      },
      "prc": {
        "ability": "wis",
        "roll": {
          "min": null,
          "max": null,
          "mode": 0
        },
        "value": 2,
        "bonuses": {
          "check": "",
          "passive": ""
        }
      },
      "prf": {
        "ability": "cha",
        "roll": {
          "min": null,
          "max": null,
          "mode": 0
        },
        "value": 0,
        "bonuses": {
          "check": "",
          "passive": ""
        }
      },
      "per": {
        "ability": "cha",
        "roll": {
          "min": null,
          "max": null,
          "mode": 0
        },
        "value": 0,
        "bonuses": {
          "check": "",
          "passive": ""
        }
      },
      "rel": {
        "ability": "int",
        "roll": {
          "min": null,
          "max": null,
          "mode": 0
        },
        "value": 0,
        "bonuses": {
          "check": "",
          "passive": ""
        }
      },
      "slt": {
        "ability": "dex",
        "roll": {
          "min": null,
          "max": null,
          "mode": 0
        },
        "value": 0,
        "bonuses": {
          "check": "",
          "passive": ""
        }
      },
      "ste": {
        "ability": "dex",
        "roll": {
          "min": null,
          "max": null,
          "mode": 0
        },
        "value": 0,
        "bonuses": {
          "check": "",
          "passive": ""
        }
      },
      "sur": {
        "ability": "wis",
        "roll": {
          "min": null,
          "max": null,
          "mode": 0
        },
        "value": 0,
        "bonuses": {
          "check": "",
          "passive": ""
        }
      }
    },
    "tools": {},
    "spells": {
      "spell1": {
        "value": 0,
        "override": null
      },
      "spell2": {
        "value": 0,
        "override": null
      },
      "spell3": {
        "value": 0,
        "override": null
      },
      "spell4": {
        "value": 0,
        "override": null
      },
      "spell5": {
        "value": 0,
        "override": null
      },
      "spell6": {
        "value": 0,
        "override": null
      },
      "spell7": {
        "value": 0,
        "override": null
      },
      "spell8": {
        "value": 0,
        "override": null
      },
      "spell9": {
        "value": 0,
        "override": null
      },
      "pact": {
        "value": 0,
        "override": null
      }
    },
    "attributes": {
      "init": {
        "ability": "",
        "roll": {
          "min": null,
          "max": null,
          "mode": 0
        },
        "bonus": ""
      },
      "movement": {
        "burrow": null,
        "climb": null,
        "fly": 20,
        "swim": null,
        "walk": 0,
        "units": "ft",
        "hover": false
      },
      "attunement": {
        "max": 3
      },
      "senses": {
        "darkvision": 120,
        "blindsight": 0,
        "tremorsense": 0,
        "truesight": 0,
        "units": "ft",
        "special": ""
      },
      "spellcasting": "int",
      "exhaustion": 0,
      "concentration": {
        "ability": "",
        "roll": {
          "min": null,
          "max": null,
          "mode": 0
        },
        "bonuses": {
          "save": ""
        },
        "limit": 1
      },
      "ac": {
        "flat": 15,
        "calc": "natural",
        "formula": ""
      },
      "hp": {
        "value": 75,
        "max": 75,
        "temp": 0,
        "tempmax": 0,
        "formula": "10d10 + 20"
      },
      "death": {
        "ability": "",
        "roll": {
          "min": null,
          "max": null,
          "mode": 0
        },
        "success": 0,
        "failure": 0
      }
    },
    "details": {
      "biography": {
        "value": "<p>If a beholder is stunned and brought to the brine pool of an elder brain, the beholder can be converted into a mindwitness. This alters some of its eye rays and transforms four of its eyestalks into tentacles similar to a mind flayer’s. The mindwitness is psychically imprinted with devotion to the elder brain and submission to illithid commands.</p>\n<p>A mindwitness’s primary function is to improve telepathic communication in a mind flayer colony. A creature in telepathic communication with a mindwitness can converse through it to as many as seven other creatures the mindwitness can see, rapidly disseminating commands and other information.</p>\n<p>If separated from its illithid masters, a mindwitness seeks out other telepathic creatures to tell it what to do. Mindwitnesses have been known to ally with flumph;flumphs (see the <em><a title=\"Monster Manual\" href=\"https://www.dndbeyond.com/sources/mm\">Monster Manual</a></em>) and planar beings such as demons, shifting their worldview and alignment to match those of their new masters.</p>",
        "public": ""
      },
      "alignment": "Typically Lawful Neutral",
      "race": null,
      "type": {
        "value": "aberration",
        "subtype": ""
      },
      "environment": "Underdark",
      "cr": 5,
      "spellLevel": 0,
      "source": {
        "book": "Mordenkainen Presents: Monsters of the Multiverse",
        "page": "181",
        "custom": "",
        "license": ""
      }
    },
    "resources": {
      "legact": {
        "value": 0,
        "max": 0
      },
      "legres": {
        "value": 0,
        "max": 0
      },
      "lair": {
        "value": false,
        "initiative": null
      }
    },
    "traits": {
      "size": "lg",
      "di": {
        "value": [],
        "bypasses": [],
        "custom": ""
      },
      "dr": {
        "value": [],
        "bypasses": [],
        "custom": ""
      },
      "dv": {
        "value": [],
        "bypasses": [],
        "custom": ""
      },
      "dm": {
        "amount": {},
        "bypasses": []
      },
      "ci": {
        "value": [
          "prone"
        ],
        "custom": ""
      },
      "languages": {
        "value": [
          "deep",
          "undercommon"
        ],
        "custom": "Telepathy 600 ft."
      }
    }
  },
  "prototypeToken": {
    "name": "Mindwitness",
    "displayName": 20,
    "actorLink": false,
    "appendNumber": false,
    "prependAdjective": false,
    "texture": {
      "src": "ddb-images/other/npc-token-Mindwitness.jpeg",
      "scaleX": 1,
      "scaleY": 1,
      "offsetX": 0,
      "offsetY": 0,
      "rotation": 0
    },
    "width": 2,
    "height": 2,
    "lockRotation": false,
    "rotation": 0,
    "alpha": 1,
    "disposition": -1,
    "displayBars": 20,
    "bar1": {
      "attribute": "attributes.hp"
    },
    "bar2": {
      "attribute": null
    },
    "light": {
      "alpha": 0.5,
      "angle": 360,
      "bright": 0,
      "coloration": 1,
      "dim": 0,
      "attenuation": 0.5,
      "luminosity": 0.5,
      "saturation": 0,
      "contrast": 0,
      "shadows": 0,
      "animation": {
        "type": null,
        "speed": 5,
        "intensity": 5,
        "reverse": false
      },
      "darkness": {
        "min": 0,
        "max": 1
      }
    },
    "sight": {
      "enabled": false,
      "range": 120,
      "angle": 360,
      "visionMode": "darkvision",
      "color": null,
      "attenuation": 0,
      "brightness": 0,
      "saturation": -1,
      "contrast": 0
    },
    "detectionModes": [],
    "flags": {
      "monks-tokenbar": {
        "include": "default"
      },
      "tagger": {
        "tags": [
          "dndbeyond",
          "ddb-importer",
          "aberration"
        ]
      }
    },
    "randomImg": false
  },
  "items": [
    {
      "_id": "I0m5A4gCNq1lLBpj",
      "name": "Multiattack",
      "type": "feat",
      "system": {
        "description": {
          "value": "<div class=\"ddb\">\n<section class=\"secret\">\n<p> The mindwitness makes one Bite attack and one Tentacles attack, or it uses Eye Ray three times.</p>\n</section>\nThe [[lookup @name]] uses [[lookup @item.name]].\n</div>",
          "chat": ""
        },
        "source": {
          "book": "Mordenkainen Presents: Monsters of the Multiverse",
          "page": "181",
          "custom": "",
          "license": ""
        },
        "activation": {
          "type": "action",
          "cost": 1,
          "condition": ""
        },
        "duration": {
          "value": "",
          "units": "inst"
        },
        "cover": null,
        "crewed": false,
        "target": {
          "value": null,
          "width": null,
          "units": "",
          "type": "",
          "prompt": true
        },
        "range": {
          "value": null,
          "long": null,
          "units": ""
        },
        "uses": {
          "value": null,
          "max": "",
          "per": null,
          "recovery": "",
          "prompt": true
        },
        "consume": {
          "type": "",
          "target": null,
          "amount": null,
          "scale": false
        },
        "ability": null,
        "actionType": null,
        "attack": {
          "bonus": "",
          "flat": false
        },
        "chatFlavor": "",
        "critical": {
          "threshold": null,
          "damage": ""
        },
        "damage": {
          "parts": [],
          "versatile": ""
        },
        "formula": "",
        "save": {
          "dc": null,
          "ability": "",
          "scaling": "flat"
        },
        "summons": null,
        "type": {
          "value": "monster",
          "subtype": ""
        },
        "properties": [],
        "requirements": "",
        "recharge": {
          "value": null,
          "charged": false
        }
      },
      "effects": [],
      "flags": {
        "ddbimporter": {
          "levelBonus": false,
          "dndbeyond": {}
        },
        "monsterMunch": {
          "titleHTML": "<strong>Multiattack.</strong>",
          "fullName": "Multiattack.",
          "actionCopy": false,
          "type": "action",
          "actionInfo": {
            "damage": {
              "parts": [],
              "versatile": ""
            },
            "baseAbility": null,
            "toHit": 0,
            "proficient": false,
            "extraAttackBonus": 0
          }
        },
        "midi-qol": {
          "removeAttackDamageButtons": "default"
        },
        "midiProperties": {
          "confirmTargets": "default"
        }
      },
      "img": "icons/skills/melee/strike-weapons-orange.webp",
      "folder": null,
      "sort": 0,
      "ownership": {
        "default": 0
      },
      "_stats": {
        "systemId": null,
        "systemVersion": null,
        "coreVersion": null,
        "createdTime": null,
        "modifiedTime": null,
        "lastModifiedBy": null
      },
      "_key": "!actors.items!OLlt8s6BCI3tnMsi.I0m5A4gCNq1lLBpj"
    },
    {
      "_id": "nSmMDmTJps1YNyzL",
      "name": "Bite",
      "type": "weapon",
      "system": {
        "description": {
          "value": "<div class=\"ddb\">\n<section class=\"secret\">\n<p><em><strong></strong> Melee Weapon Attack:</em> +5 to hit, reach 5 ft., one creature. <em>Hit:</em> [[/damage 4d6 + @mod type=piercing average=true]] damage.</p>\n</section>\nThe [[lookup @name]] attacks with its [[lookup @item.name]].\n</div>",
          "chat": ""
        },
        "source": {
          "book": "Mordenkainen Presents: Monsters of the Multiverse",
          "page": "181",
          "custom": "",
          "license": ""
        },
        "identified": true,
        "unidentified": {
          "description": ""
        },
        "container": null,
        "quantity": 1,
        "weight": 0,
        "price": {
          "value": 0,
          "denomination": "gp"
        },
        "rarity": "",
        "attunement": 0,
        "equipped": true,
        "activation": {
          "type": "action",
          "cost": 1,
          "condition": ""
        },
        "duration": {
          "value": "",
          "units": "inst"
        },
        "cover": null,
        "crewed": false,
        "target": {
          "value": null,
          "width": null,
          "units": "",
          "type": "",
          "prompt": true
        },
        "range": {
          "value": 5,
          "long": null,
          "units": "ft"
        },
        "uses": {
          "value": null,
          "max": "",
          "per": null,
          "recovery": "",
          "prompt": true
        },
        "consume": {
          "type": "",
          "target": null,
          "amount": null,
          "scale": false
        },
        "ability": "dex",
        "actionType": "mwak",
        "attack": {
          "bonus": "",
          "flat": false
        },
        "chatFlavor": "",
        "critical": {
          "threshold": null,
          "damage": ""
        },
        "damage": {
          "parts": [
            [
              "4d6[piercing] + @mod",
              "piercing"
            ]
          ],
          "versatile": ""
        },
        "formula": "",
        "save": {
          "dc": null,
          "ability": "",
          "scaling": "flat"
        },
        "summons": null,
        "armor": {
          "value": null
        },
        "hp": {
          "value": null,
          "max": null,
          "dt": null,
          "conditions": ""
        },
        "type": {
          "value": "natural",
          "baseItem": ""
        },
        "magicalBonus": null,
        "properties": [],
        "proficient": 1
      },
      "effects": [],
      "flags": {
        "ddbimporter": {
          "levelBonus": false,
          "dndbeyond": {}
        },
        "monsterMunch": {
          "titleHTML": "<strong>Bite.</strong>",
          "fullName": "Bite.",
          "actionCopy": false,
          "type": "action",
          "actionInfo": {
            "damage": {
              "parts": [
                [
                  "4d6[piercing] + @mod",
                  "piercing"
                ]
              ],
              "versatile": ""
            },
            "baseAbility": "dex",
            "toHit": 5,
            "proficient": true,
            "extraAttackBonus": 0
          }
        },
        "midi-qol": {
          "removeAttackDamageButtons": "default"
        },
        "midiProperties": {
          "confirmTargets": "default"
        }
      },
      "img": "icons/creatures/abilities/mouth-teeth-long-red.webp",
      "folder": null,
      "sort": 0,
      "ownership": {
        "default": 0
      },
      "_stats": {
        "systemId": null,
        "systemVersion": null,
        "coreVersion": null,
        "createdTime": null,
        "modifiedTime": null,
        "lastModifiedBy": null
      },
      "_key": "!actors.items!OLlt8s6BCI3tnMsi.nSmMDmTJps1YNyzL"
    },
    {
      "_id": "inp4efRu3RpsqwSd",
      "name": "Tentacles",
      "type": "weapon",
      "system": {
        "description": {
          "value": "<div class=\"ddb\">\n<section class=\"secret\">\n<p><em><strong></strong> Melee Weapon Attack:</em> +5 to hit, reach 5 ft., one creature. <em>Hit:</em> [[/damage 4d8 + @mod type=psychic average=true]] damage. If the target is Large or smaller, it is &amp;Reference[grappled]{grappled} (escape DC 13) and must succeed on a [[/save int 13 format=long]] or be &amp;Reference[restrained]{restrained} until this grapple ends.</p>\n</section>\nThe [[lookup @name]] attacks with its [[lookup @item.name]].\n</div>",
          "chat": ""
        },
        "source": {
          "book": "Mordenkainen Presents: Monsters of the Multiverse",
          "page": "181",
          "custom": "",
          "license": ""
        },
        "identified": true,
        "unidentified": {
          "description": ""
        },
        "container": null,
        "quantity": 1,
        "weight": 0,
        "price": {
          "value": 0,
          "denomination": "gp"
        },
        "rarity": "",
        "attunement": 0,
        "equipped": true,
        "activation": {
          "type": "action",
          "cost": 1,
          "condition": ""
        },
        "duration": {
          "units": "round",
          "value": "10"
        },
        "cover": null,
        "crewed": false,
        "target": {
          "value": null,
          "width": null,
          "units": "",
          "type": "",
          "prompt": true
        },
        "range": {
          "value": 5,
          "long": null,
          "units": "ft"
        },
        "uses": {
          "value": null,
          "max": "",
          "per": null,
          "recovery": "",
          "prompt": true
        },
        "consume": {
          "type": "",
          "target": null,
          "amount": null,
          "scale": false
        },
        "ability": "dex",
        "actionType": "mwak",
        "attack": {
          "bonus": "",
          "flat": false
        },
        "chatFlavor": "",
        "critical": {
          "threshold": null,
          "damage": ""
        },
        "damage": {
          "parts": [
            [
              "4d8[psychic] + @mod",
              "psychic"
            ]
          ],
          "versatile": ""
        },
        "formula": "",
        "save": {
          "dc": 13,
          "ability": "int",
          "scaling": "flat"
        },
        "summons": null,
        "armor": {
          "value": null
        },
        "hp": {
          "value": null,
          "max": null,
          "dt": null,
          "conditions": ""
        },
        "type": {
          "value": "natural",
          "baseItem": ""
        },
        "magicalBonus": null,
        "properties": [],
        "proficient": 1
      },
      "effects": [
        {
          "changes": [
            {
              "key": "macro.CE",
              "mode": 0,
              "value": "Restrained",
              "priority": 20
            }
          ],
          "duration": {
            "seconds": 60,
            "startTime": null,
            "rounds": 10,
            "turns": null,
            "startRound": null,
            "startTurn": null,
            "combat": null
          },
          "tint": null,
          "transfer": false,
          "disabled": false,
          "flags": {
            "dae": {
              "transfer": false,
              "stackable": "noneName"
            },
            "ddbimporter": {
              "disabled": false
            },
            "midi-qol": {
              "forceCEOff": true
            },
            "core": {}
          },
          "name": "Tentacles",
          "statuses": [],
          "icon": "icons/commodities/biological/tentacle-purple-white.webp",
          "_id": "KvVgWmkqIJ8n6sZN",
          "description": "",
          "origin": null,
          "_key": "!actors.items.effects!OLlt8s6BCI3tnMsi.inp4efRu3RpsqwSd.KvVgWmkqIJ8n6sZN"
        }
      ],
      "flags": {
        "ddbimporter": {
          "levelBonus": false,
          "dndbeyond": {},
          "effectsApplied": true
        },
        "monsterMunch": {
          "titleHTML": "<strong>Tentacles.</strong>",
          "fullName": "Tentacles.",
          "actionCopy": false,
          "type": "action",
          "actionInfo": {
            "damage": {
              "parts": [
                [
                  "4d8[psychic] + @mod",
                  "psychic"
                ]
              ],
              "versatile": ""
            },
            "baseAbility": "dex",
            "toHit": 5,
            "proficient": true,
            "extraAttackBonus": 0
          }
        },
        "midi-qol": {
          "removeAttackDamageButtons": "default",
          "forceCEOff": true
        },
        "midiProperties": {
          "confirmTargets": "default",
          "fulldam": true
        }
      },
      "img": "icons/commodities/biological/tentacle-purple-white.webp",
      "folder": null,
      "sort": 0,
      "ownership": {
        "default": 0
      },
      "_stats": {
        "systemId": null,
        "systemVersion": null,
        "coreVersion": null,
        "createdTime": null,
        "modifiedTime": null,
        "lastModifiedBy": null
      },
      "_key": "!actors.items!OLlt8s6BCI3tnMsi.inp4efRu3RpsqwSd"
    },
    {
      "_id": "4T0KL6wmpuSUoR63",
      "name": "Eye Ray",
      "type": "feat",
      "system": {
        "description": {
          "value": "<div class=\"ddb\">\n<section class=\"secret\">\n<p> The mindwitness shoots one magical eye ray at random (roll a d6, and reroll if the ray has already been used this turn), choosing one target it can see within 120 feet of it:</p><p><strong>1: Aversion Ray. </strong>The targeted creature must make a [[/save cha 13 format=long]]. On a failed save, the target has disadvantage on attack rolls for 1 minute. The target can repeat the saving throw at the end of each of its turns, ending the effect on itself on a success.</p><p><strong>2: Fear Ray. </strong>The targeted creature must succeed on a [[/save wis 13 format=long]] or be &amp;Reference[frightened]{frightened} for 1 minute. The target can repeat the saving throw at the end of each of its turns, ending the effect on itself on a success.</p><p><strong>3: &amp;Reference[psychic]{Psychic} Ray. </strong>The target must succeed on a [[/save int 13 format=long]] or take [[/damage 6d8 type=psychic average=true]] damage.</p><p><strong>4: Slowing Ray. </strong>The targeted creature must make a [[/save dex 13 format=long]]. On a failed save, the target’s speed is halved for 1 minute. In addition, the creature can’t take reactions, and it can take either an action or a bonus action on its turn but not both. The creature can repeat the saving throw at the end of each of its turns, ending the effect on itself on a success.</p><p><strong>5: Stunning Ray. </strong>The targeted creature must succeed on a [[/save con 13 format=long]] or be &amp;Reference[stunned]{stunned} for 1 minute. The target can repeat the saving throw at the start of each of its turns, ending the effect on itself on a success.</p><p><strong>6: Telekinetic Ray. </strong>If the target is a creature, it must make a [[/save str 13 format=long]]. On a failed save, the mindwitness moves it up to 30 feet in any direction, and it is &amp;Reference[restrained]{restrained} by the ray’s telekinetic grip until the start of the mindwitness’s next turn or until the mindwitness is &amp;Reference[incapacitated]{incapacitated}.</p><p>If the target is an object weighing 300 pounds or less that isn’t being worn or carried, it is telekinetically moved up to 30 feet in any direction. The mindwitness can also exert fine control on objects with this ray, such as manipulating a simple tool or opening a door or a container.</p>\n</section>\nThe [[lookup @name]] uses [[lookup @item.name]] and a save is required.\n</div>",
          "chat": ""
        },
        "source": {
          "book": "Mordenkainen Presents: Monsters of the Multiverse",
          "page": "181",
          "custom": "",
          "license": ""
        },
        "activation": {
          "type": "action",
          "cost": 1,
          "condition": ""
        },
        "duration": {
          "units": "round",
          "value": "10"
        },
        "cover": null,
        "crewed": false,
        "target": {
          "value": null,
          "width": null,
          "units": "",
          "type": "",
          "prompt": true
        },
        "range": {
          "value": 120,
          "long": null,
          "units": "ft"
        },
        "uses": {
          "value": null,
          "max": "",
          "per": null,
          "recovery": "",
          "prompt": true
        },
        "consume": {
          "type": "",
          "target": null,
          "amount": null,
          "scale": false
        },
        "ability": null,
        "actionType": "save",
        "attack": {
          "bonus": "",
          "flat": false
        },
        "chatFlavor": "",
        "critical": {
          "threshold": null,
          "damage": ""
        },
        "damage": {
          "parts": [
            [
              "6d8[psychic]",
              "psychic"
            ]
          ],
          "versatile": ""
        },
        "formula": "",
        "save": {
          "dc": 13,
          "ability": "cha",
          "scaling": "flat"
        },
        "summons": null,
        "type": {
          "value": "monster",
          "subtype": ""
        },
        "properties": [],
        "requirements": "",
        "recharge": {
          "value": null,
          "charged": false
        }
      },
      "effects": [
        {
          "changes": [
            {
              "key": "macro.CE",
              "mode": 0,
              "value": "Frightened",
              "priority": 20
            },
            {
              "key": "flags.midi-qol.OverTime",
              "mode": 5,
              "value": "turn=end,label=Eye Ray (End of Turn),saveRemove=true,saveDC=13,saveAbility=wis,killAnim=true",
              "priority": 20
            }
          ],
          "duration": {
            "seconds": 60,
            "startTime": null,
            "rounds": 10,
            "turns": null,
            "startRound": null,
            "startTurn": null,
            "combat": null
          },
          "tint": null,
          "transfer": false,
          "disabled": false,
          "flags": {
            "dae": {
              "transfer": false,
              "stackable": "noneName",
              "specialDuration": [
                "turnStartSource"
              ]
            },
            "ddbimporter": {
              "disabled": false
            },
            "midi-qol": {
              "forceCEOff": true
            },
            "core": {}
          },
          "name": "Eye Ray",
          "statuses": [],
          "icon": "icons/magic/perception/eye-tendrils-web-purple.webp",
          "_id": "mR9tGh3u3Nj2PHdv",
          "description": "",
          "origin": null,
          "_key": "!actors.items.effects!OLlt8s6BCI3tnMsi.4T0KL6wmpuSUoR63.mR9tGh3u3Nj2PHdv"
        }
      ],
      "flags": {
        "ddbimporter": {
          "levelBonus": false,
          "dndbeyond": {},
          "effectsApplied": true
        },
        "monsterMunch": {
          "titleHTML": "<strong>Eye Ray.</strong>",
          "fullName": "Eye Ray.",
          "actionCopy": false,
          "type": "action",
          "actionInfo": {
            "damage": {
              "parts": [
                [
                  "6d8[psychic]",
                  "psychic"
                ]
              ],
              "versatile": ""
            },
            "baseAbility": null,
            "toHit": 0,
            "proficient": false,
            "extraAttackBonus": 0
          }
        },
        "midi-qol": {
          "removeAttackDamageButtons": "default",
          "forceCEOff": true
        },
        "midiProperties": {
          "confirmTargets": "default",
          "fulldam": true
        }
      },
      "img": "icons/magic/perception/eye-tendrils-web-purple.webp",
      "folder": null,
      "sort": 0,
      "ownership": {
        "default": 0
      },
      "_stats": {
        "systemId": null,
        "systemVersion": null,
        "coreVersion": null,
        "createdTime": null,
        "modifiedTime": null,
        "lastModifiedBy": null
      },
      "_key": "!actors.items!OLlt8s6BCI3tnMsi.4T0KL6wmpuSUoR63"
    },
    {
      "_id": "NVYOoaGV5dCeGm4v",
      "name": "Telepathic Hub",
      "type": "feat",
      "system": {
        "description": {
          "value": "<div class=\"ddb\">\n<section class=\"secret\">\n<p><em><strong>Telepathic Hub.</strong></em> When the mindwitness receives a telepathic message, it can telepathically share that message with up to seven other creatures within 600 feet of it that it can see.</p>\n</section>\nThe [[lookup @name]] uses [[lookup @item.name]].\n</div>",
          "chat": ""
        },
        "source": {
          "book": "Mordenkainen Presents: Monsters of the Multiverse",
          "page": "181",
          "custom": "",
          "license": ""
        },
        "activation": {
          "cost": null,
          "type": "",
          "condition": ""
        },
        "duration": {
          "value": "",
          "units": ""
        },
        "cover": null,
        "crewed": false,
        "target": {
          "value": null,
          "width": null,
          "units": "",
          "type": "",
          "prompt": true
        },
        "range": {
          "value": null,
          "long": null,
          "units": ""
        },
        "uses": {
          "value": null,
          "max": "",
          "per": null,
          "recovery": "",
          "prompt": true
        },
        "consume": {
          "type": "",
          "target": null,
          "amount": null,
          "scale": false
        },
        "ability": null,
        "actionType": null,
        "attack": {
          "bonus": "",
          "flat": false
        },
        "chatFlavor": "",
        "critical": {
          "threshold": null,
          "damage": ""
        },
        "damage": {
          "parts": [],
          "versatile": ""
        },
        "formula": "",
        "save": {
          "dc": null,
          "ability": "",
          "scaling": "flat"
        },
        "summons": null,
        "type": {
          "value": "monster",
          "subtype": ""
        },
        "properties": [],
        "requirements": "",
        "recharge": {
          "value": null,
          "charged": false
        }
      },
      "effects": [],
      "flags": {
        "ddbimporter": {
          "levelBonus": false,
          "dndbeyond": {}
        },
        "monsterMunch": {
          "titleHTML": "<em><strong>Telepathic Hub.</strong></em>",
          "fullName": "Telepathic Hub.",
          "actionCopy": false,
          "type": "special",
          "actionInfo": {
            "damage": {
              "parts": [],
              "versatile": ""
            },
            "baseAbility": null,
            "toHit": 0,
            "proficient": false,
            "extraAttackBonus": 0
          }
        },
        "midi-qol": {
          "removeAttackDamageButtons": "default"
        },
        "midiProperties": {
          "confirmTargets": "default"
        }
      },
      "img": "icons/magic/death/skull-poison-green.webp",
      "folder": null,
      "sort": 0,
      "ownership": {
        "default": 0
      },
      "_stats": {
        "systemId": null,
        "systemVersion": null,
        "coreVersion": null,
        "createdTime": null,
        "modifiedTime": null,
        "lastModifiedBy": null
      },
      "_key": "!actors.items!OLlt8s6BCI3tnMsi.NVYOoaGV5dCeGm4v"
    }
  ],
  "effects": [],
  "folder": "ESzjRzm6DRDI0Q26",
  "sort": 0,
  "ownership": {
    "default": 0,
    "6yhz13iFYYklKtgA": 3
  },
  "flags": {
    "dnd5e": {},
    "monsterMunch": {
      "url": "https://www.dndbeyond.com/monsters/2560874-mindwitness",
      "img": "https://www.dndbeyond.com/avatars/25746/533/637880557825677939.png",
      "tokenImg": "https://www.dndbeyond.com/avatars/25746/532/637880557824397792.jpeg",
      "isStockImg": false,
      "spellList": {
        "class": [],
        "pact": [],
        "atwill": [],
        "innate": [],
        "edgeCases": [],
        "material": true,
        "innateMatch": false
      },
      "overTime": [
        "Tentacles",
        "Eye Ray"
      ]
    },
    "ddbimporter": {
      "id": 2560874,
      "entityTypeId": 779871897,
      "creatureGroupId": null,
      "creatureFlags": [],
      "version": "5.1.27",
      "isLegacy": false,
      "flatAC": false
    }
  },
  "_stats": {
    "systemId": "dnd5e",
    "systemVersion": "3.1.2",
    "coreVersion": "11.315",
    "createdTime": 1721275300094,
    "modifiedTime": 1721275300094,
    "lastModifiedBy": "6yhz13iFYYklKtgA"
  },
  "_key": "!actors!OLlt8s6BCI3tnMsi"
}
